Workbook

Sheet Start Here
A1: Social Media Plan — Muhammad Mehrooz Shafique | Permanent SEO
A2: 6-month content calendar (Nov 2026 – Apr 2027) · LinkedIn + Instagram primary · cross-post to X, Facebook, YouTube, Reddit
A4: Brand
A5: Name on posts | B5: Muhammad Mehrooz Shafique
A6: Title | B6: SEO Expert · Co-Founder, Permanent SEO
A7: Audience | B7: E-commerce brands (Shopify, WooCommerce, online stores)
A8: Tone | B8: Confident expert. Short sentences. No fluff, no hype words, no invented stats.
A9: Brand lead | B9: Personal brand first; Permanent SEO credited on every post (logo + name tag).
A10: Call to action | B10: Every post: Comment "KEYWORD" → send that post's freebie by DM. Keyword changes per post.
A11: Colours
A12: Primary blue | B12: #1566D7 (your final brand blue — buttons, highlights, key words)
A13: Logo blue (gradient top) | B13: #345DF5
A14: Deep navy (gradient bottom / text) | B14: #191A46
A15: Mid blue | B15: #2B43B1
A16: Light background | B16: #F4F7FD
A17: White / Ink | B17: #FFFFFF / #0B0F1F
A18: Typography
A19: Headlines | B19: Bebas Neue or Anton (condensed, high impact, ALL CAPS)
A20: Body | B20: Inter (Regular/SemiBold)
A21: Photo use | B21: Small circular headshot avatar + name tag bottom-left; logo bottom-right
A22: Visual styles
A23: LinkedIn image & slides | B23: Light editorial: off-white background, navy text, blue accents, data charts, UI mockups, guide-cover layouts
A24: Instagram posts & slides | B24: Bold creator: #345DF5 → #191A46 gradient, giant white condensed headline, blue highlights
A25: Reels | B25: Monochrome studio + 3D objects + kinetic text, one blue accent, calm deep male voiceover (Solution-Wagon-style reference)
A26: Long videos | B26: Bright motion-graphics explainer with UI mockups, blue key words (BlogSEO-style reference)
A28: Plan at a glance (live counts)
A29: Metric | B29: Value
A30: Total posting days | B30: =COUNTA('Content Calendar'!B5:B134) -> 130
A31: Slide posts (Mon) | B31: =COUNTIF('Content Calendar'!H5:H134,"SLIDE") -> 26
A32: Image posts (Tue/Fri) | B32: =COUNTIF('Content Calendar'!H5:H134,"POST") -> 52
A33: Reels (Wed) | B33: =COUNTIF('Content Calendar'!H5:H134,"REEL") -> 26
A34: Long videos (Thu) | B34: =COUNTIF('Content Calendar'!H5:H134,"LONG_VIDEO") -> 26
A35: Posted so far | B35: =COUNTIF('Content Calendar'!AH5:AH134,"Posted") -> 0
A36: Scheduled | B36: =COUNTIF('Content Calendar'!AH5:AH134,"Scheduled") -> 0
A37: Progress | B37: =IFERROR(B35/B30,0) -> 0
A39: How to use
A40: 1. Open 'Content Calendar'. Each row = one posting day (Mon–Fri, 5x/week).
A41: 2. Copy 'LinkedIn Visual/Video Prompt' or 'Instagram Visual/Video Prompt' into your image/video AI tool (Canva, Higgsfield, Midjourney, Nano Banana, Kling, etc.). Upload your headshot + logo as references.
A42: 3. Copy the caption columns as-is. Hashtags are already at the end of each caption (also listed separately).
A43: 4. Cross-post using the X / Facebook / YouTube / Reddit columns on the same row.
A44: 5. Prepare the freebie listed in 'Freebies Tracker' BEFORE the post goes live; DM it to everyone who comments the keyword.
A45: 6. Replace every [PLACEHOLDER] (client results, your data) with real numbers. Never publish a placeholder.
A46: 7. Update 'Status' (dropdown) — the counts above update automatically.
A47: 8. Need a new post? Use 'Prompt Templates' column C (writing) then column D (visual).
A48: Legend: editable cells = Status and Posted URL / Notes (yellow headers) on the calendar. Row colours: blue = Slide, white = Post, green = Reel, orange = Long video.

Sheet Content Calendar
A1: Content Calendar — Nov 2026 to Apr 2027 (5 posts/week)
A2: Captions are ready to post. Replace [placeholders] before publishing. Times are UK time — starting points to test.
A4: # | B4: Date | C4: Day | D4: Week | E4: Month | F4: Monthly Theme | G4: Pillar | H4: Format | I4: LinkedIn Format | J4: Instagram Format | K4: Topic | L4: Hook / Cover Headline | M4: Primary Keyword | N4: Secondary Keywords | O4: LinkedIn Caption (ready) | P4: LinkedIn Hashtags | Q4: Instagram Caption (ready) | R4: Instagram Hashtags | S4: Production Brief (slides / script) | T4: LinkedIn Visual/Video Prompt (ready) | U4: Instagram Visual/Video Prompt (ready) | V4: Comment Keyword | W4: Freebie | X4: X Post / Thread | Y4: Facebook | Z4: Cross-post To | AA4: YouTube Title | AB4: YouTube Description | AC4: YouTube Tags | AD4: Reddit Subreddit | AE4: Reddit Title | AF4: Reddit Post | AG4: Post Time (LI / IG) | AH4: Status | AI4: Posted URL / Notes
A5: 1 | B5: 46328 | C5: Mon | D5: 1 | E5: Nov 2026 | F5: E-commerce SEO Foundations + Black Friday / Cyber Monday SEO | G5: Educate | H5: SLIDE | I5: LinkedIn Slide Post (PDF carousel) | J5: Instagram Slide Post (carousel) | K5: Meet Mehrooz: 8 reasons e-commerce stores lose organic traffic | L5: Your store isn't invisible by accident. Here are 8 reasons why. | M5: why is my store losing organic traffic | N5: ecommerce SEO, Shopify organic traffic drop, online store SEO problems, ecommerce traffic decline | O5: I'm Muhammad Mehrooz Shafique, Co-Founder of Permanent SEO. I work with e-commerce brands on one thing: organic traffic that stays. On this account I'll teach store owners how SEO actually works for online shops. Technical fixes. Product and category pages. Seasonal SEO. AI search. Real case breakdowns. To start, here's what I see most often when a store's organic traffic slides: → Collection pages with no unique content → Duplicate URLs from filters and variants → Seasonal pages deleted after every sale → Out-of-stock products returning 404s → Slow mobile pages loaded with apps → No internal links pointing to money pages → Product titles written for the brand, not the buyer → Nobody checking Google Search Console None of these need a bigger budget. They need someone to look. This month is all about e-commerce SEO foundations and getting ready for Black Friday and Cyber Monday. Swipe through the carousel. Then check your own store against it. Comment "LEAKS" and I'll send you the E-commerce Organic Traffic Leak Checklist. #EcommerceSEO #ShopifySEO #OrganicTraffic #PermanentSEO | P5: #EcommerceSEO #ShopifySEO #OrganicTraffic #PermanentSEO | Q5: 8 reasons your store is losing organic traffic. → Thin collection pages → Filter and variant duplicates → Deleted seasonal pages → 404s on out-of-stock products → Slow, app-heavy mobile pages I'm Mehrooz, Co-Founder of Permanent SEO. I'll be teaching e-commerce SEO here every weekday. Save this and check your store tonight. Comment "LEAKS" for the E-commerce Organic Traffic Leak Checklist. #ecommerceseo #seotips #shopifyseo #onlinestore #ecommercetips #organictraffic #smallbusinessseo #shopifystore #woocommerce #seoexpert #ecommercemarketing #storeowner | R5: #ecommerceseo #seotips #shopifyseo #onlinestore #ecommercetips #organictraffic #smallbusinessseo #shopifystore #woocommerce #seoexpert #ecommercemarketing #storeowner | S5: Slide 1: Your store isn't invisible by accident. | 8 reasons e-commerce stores lose organic traffic. Photo of Mehrooz, name + "Co-Founder, Permanent SEO" Slide 2: Who I am | Muhammad Mehrooz Shafique. I help e-commerce brands build organic traffic that stays. This account: store SEO, seasonal SEO, AI search, real breakdowns. Slide 3: Reason 1: Thin collection pages | A grid of products and no text. Google can't tell what the page is about or why it should rank. Slide 4: Reason 2: Duplicate URLs | Filters, sorting and variants create hundreds of near-identical URLs. Check canonicals. Slide 5: Reason 3: Deleted seasonal pages | Every January the Black Friday page gets deleted. Every November you start from zero. Slide 6: Reason 4: Out-of-stock 404s | Removing products kills links and rankings. Keep the page, show alternatives. Slide 7: Reason 5 + 6: Speed and internal links | Slow mobile pages lose visitors. Money pages with no internal links lose rankings. Slide 8: Reason 7 + 8: Titles and blind spots | Product titles nobody searches for. No one opening Google Search Console. Slide 9: The fix starts with a check | Not a bigger budget. A 30-minute look at the right reports. Slide 10: Comment "LEAKS" | Get the E-commerce Organic Traffic Leak Checklist. Follow Mehrooz for daily e-commerce SEO. | T5: Design a 10-slide LinkedIn PDF carousel, 1080x1350 each. Clean premium editorial style: off-white #F4F7FD background, primary blue #1566D7 accents, navy #191A46 text, headlines in Bebas Neue (bold condensed, all caps), body in Inter; generous margins, faint grid lines, crisp vector icons, no stock-photo clutter. Cover slide like a premium guide cover: giant two-tone headline (key word in blue), small illustration/UI mockup, numbered contents list. Inner slides: big slide number in blue, Bebas Neue title, short Inter body, one diagram/mockup/checklist per slide. Last slide: navy CTA banner with download icon. SLIDE CONTENT: Slide 1: Your store isn't invisible by accident. | 8 reasons e-commerce stores lose organic traffic. Photo of Mehrooz, name + "Co-Founder, Permanent SEO" Slide 2: Who I am | Muhammad Mehrooz Shafique. I help e-commerce brands build organic traffic that stays. This account: store SEO, seasonal SEO, AI search, real breakdowns. Slide 3: Reason 1: Thin collection pages | A grid of products and no text. Google can't tell what the page is about or why it should rank. Slide 4: Reason 2: Duplicate URLs | Filters, sorting and variants create hundreds of near-identical URLs. Check canonicals. Slide 5: Reason 3: Deleted seasonal pages | Every January the Black Friday page gets deleted. Every November you start from zero. Slide 6: Reason 4: Out-of-stock 404s | Removing products kills links and rankings. Keep the page, show alternatives. Slide 7: Reason 5 + 6: Speed and internal links | Slow mobile pages lose visitors. Money pages with no internal links lose rankings. Slide 8: Reason 7 + 8: Titles and blind spots | Product titles nobody searches for. No one opening Google Search Console. Slide 9: The fix starts with a check | Not a bigger budget. A 30-minute look at the right reports. Slide 10: Comment "LEAKS" | Get the E-commerce Organic Traffic Leak Checklist. Follow Mehrooz for daily e-commerce SEO. Footer on every frame: small circular headshot avatar + name tag 'Muhammad Mehrooz Shafique · Co-Founder, Permanent SEO' bottom-left; Permanent SEO 'P' logo (rising bar-chart + arrow mark) bottom-right. All text spelled exactly as written, sharp and legible on mobile; no extra words, no watermarks. | U5: Design a 10-slide Instagram carousel, 1080x1350 each. Bold creator style: deep gradient background #345DF5 (top) to #191A46 (bottom), huge white Bebas Neue / Anton condensed headline, key words highlighted in #1566D7 highlight boxes or light-blue text, high contrast. Slide 1 = scroll-stopping cover with giant condensed headline and a 'swipe →' cue; inner slides alternate navy and white backgrounds, big blue slide number, max 25 words, one icon or mini-diagram each; last slide = CTA with comment keyword in a blue pill. SLIDE CONTENT: Slide 1: Your store isn't invisible by accident. | 8 reasons e-commerce stores lose organic traffic. Photo of Mehrooz, name + "Co-Founder, Permanent SEO" Slide 2: Who I am | Muhammad Mehrooz Shafique. I help e-commerce brands build organic traffic that stays. This account: store SEO, seasonal SEO, AI search, real breakdowns. Slide 3: Reason 1: Thin collection pages | A grid of products and no text. Google can't tell what the page is about or why it should rank. Slide 4: Reason 2: Duplicate URLs | Filters, sorting and variants create hundreds of near-identical URLs. Check canonicals. Slide 5: Reason 3: Deleted seasonal pages | Every January the Black Friday page gets deleted. Every November you start from zero. Slide 6: Reason 4: Out-of-stock 404s | Removing products kills links and rankings. Keep the page, show alternatives. Slide 7: Reason 5 + 6: Speed and internal links | Slow mobile pages lose visitors. Money pages with no internal links lose rankings. Slide 8: Reason 7 + 8: Titles and blind spots | Product titles nobody searches for. No one opening Google Search Console. Slide 9: The fix starts with a check | Not a bigger budget. A 30-minute look at the right reports. Slide 10: Comment "LEAKS" | Get the E-commerce Organic Traffic Leak Checklist. Follow Mehrooz for daily e-commerce SEO. Footer on every frame: small circular headshot avatar + name tag 'Muhammad Mehrooz Shafique · Co-Founder, Permanent SEO' bottom-left; Permanent SEO 'P' logo (rising bar-chart + arrow mark) bottom-right. All text spelled exactly as written, sharp and legible on mobile; no extra words, no watermarks. | V5: LEAKS | W5: E-commerce Organic Traffic Leak Checklist (PDF, 8 checks) | X5: I'm Mehrooz, Co-Founder of Permanent SEO. I help e-commerce stores get organic traffic that stays. First thread: 8 reasons stores lose organic traffic. --- 1. Thin collection pages. A product grid with no text gives Google nothing to rank. 2. Duplicate URLs. Filters, sorting and variants create near-identical pages. Check your canonicals. --- 3. Deleted seasonal pages. Delete the Black Friday page in January and you start from zero every November. 4. Out-of-stock 404s. Keep the URL. Show alternatives. --- 5. Slow mobile pages. Every app adds weight. 6. No internal links to money pages. If you don't link to it, Google treats it as less important. --- 7. Product titles nobody searches for. 8. Nobody opening Google Search Console. None of this needs more budget. It needs a check. #EcommerceSEO | Y5: Repost the Instagram caption + same visual | Z5: X thread · Facebook carousel · Reddit text post | AD5: r/ecommerce | AE5: The 8 most common reasons I see e-commerce stores lose organic traffic | AF5: I audit online stores for a living, mostly Shopify and WooCommerce. The same issues show up again and again when organic traffic slides, so here's the list. 1. Collection pages with zero unique text. Just a product grid. 2. Duplicate URLs from filters, sort parameters and variants, with weak or missing canonicals. 3. Seasonal pages (Black Friday, Christmas) deleted after the sale, so every year starts with no history. 4. Out-of-stock products removed and left as 404s, losing their links. 5. Slow mobile pages, usually from too many apps and scripts. 6. Important category pages with almost no internal links. 7. Product titles written in brand language instead of the words buyers search. 8. Nobody checking Google Search Console, so drops go unnoticed for months. Most of these are fixable in an afternoon once you know where to look. Search Console's Pages report and Performance report catch most of them. Which of these have you run into on your own store, and did fixing it change anything? | AG5: 08:30 / 12:30 | AH5: Planned
A6: 2 | B6: 46329 | C6: Tue | D6: 1 | E6: Nov 2026 | F6: E-commerce SEO Foundations + Black Friday / Cyber Monday SEO | G6: Data & Insight | H6: POST | I6: LinkedIn Post (detailed image) | J6: Instagram Post (single image) | K6: The 10-point store SEO audit you can run in one hour | L6: The 10-point store SEO audit. One hour. No tools you don't have. | M6: ecommerce SEO audit checklist | N6: Shopify SEO audit, online store SEO audit, ecommerce technical SEO, store SEO checklist | O6: Most store owners think an SEO audit needs expensive software. It doesn't. The basics need Google Search Console, a browser and one hour. Here's the 10-point check I start every store audit with: 1. Pages report: how many URLs are indexed vs not indexed 2. Top 20 queries: are they buying queries or random ones 3. Homepage title tag: does it say what you sell 4. Collection pages: is there unique text above or below the grid 5. Product titles: do they match how buyers search 6. Canonicals on filtered URLs 7. Out-of-stock products: live page or 404 8. Core Web Vitals report on mobile 9. Internal links to your top 5 collections 10. Last year's seasonal URLs: still live or deleted If you find problems in 3 or more, your store is leaving organic revenue on the table. The image breaks down where to find each one. Comment "STORECHECK" and I'll send you the 10-Point Store SEO Audit Sheet. #EcommerceSEO #SEOAudit #ShopifySEO #GoogleSearchConsole | P6: #EcommerceSEO #SEOAudit #ShopifySEO #GoogleSearchConsole | Q6: The 10-point store SEO audit. → Indexed vs not indexed pages → Top 20 queries: buying or random? → Unique text on collection pages → Canonicals on filter URLs → Out-of-stock pages: live or 404? One hour. Search Console and a browser. Fix the cheapest problems first. Save this for your next quiet afternoon. Comment "STORECHECK" for the 10-Point Store SEO Audit Sheet. #seoaudit #ecommerceseo #shopifyseo #seotips #onlinestore #woocommerce #googlesearchconsole #ecommercetips #technicalseo #storeowner #shopifytips #digitalmarketing | R6: #seoaudit #ecommerceseo #shopifyseo #seotips #onlinestore #woocommerce #googlesearchconsole #ecommercetips #technicalseo #storeowner #shopifytips #digitalmarketing | S6: Single image, 1080x1350 (IG) and 1200x1500 (LinkedIn). Style: clean checklist infographic, dark navy background, white text, one accent colour (green ticks). Headline (top, bold condensed): THE 10-POINT STORE SEO AUDIT Sub-headline: One hour. Google Search Console + a browser. Numbered list in two columns, each item = check + where to find it: 1. Indexed vs not indexed | GSC > Pages 2. Top 20 queries | GSC > Performance > Queries 3. Homepage title tag | View source / browser tab 4. Collection page text | Your top 5 collections 5. Product titles vs searches | GSC queries vs product names 6. Canonicals on filter URLs | View source on a filtered URL 7. Out-of-stock handling | Visit 3 sold-out products 8. Mobile Core Web Vitals | GSC > Core Web Vitals 9. Internal links to top collections | Homepage + menu + blog 10. Last year's seasonal URLs | Type /black-friday into your domain Bottom bar: "3+ problems = organic revenue left on the table" | Footer: Mehrooz Shafique · Permanent SEO | Banner: Comment "STORECHECK" for the audit sheet | T6: Create a 1080x1350 LinkedIn infographic. Clean premium editorial style: off-white #F4F7FD background, primary blue #1566D7 accents, navy #191A46 text, headlines in Bebas Neue (bold condensed, all caps), body in Inter; generous margins, faint grid lines, crisp vector icons, no stock-photo clutter. HEADLINE: "The 10-point store SEO audit. One hour. No tools you don't have." SUBHEAD: "The 10-point store SEO audit you can run in one hour" MAIN VISUAL: the layout described below containing exactly: Single image, 1080x1350 (IG) and 1200x1500 (LinkedIn). Style: clean checklist infographic, dark navy background, white text, one accent colour (green ticks). Headline (top, bold condensed): THE 10-POINT STORE SEO AUDIT Sub-headline: One hour. Google Search Console + a browser. Numbered list in two columns, each item = check + where to find it: 1. Indexed vs not indexed | GSC > Pages 2. Top 20 queries | GSC > Performance > Queries 3. Homepage title tag | View source / browser tab 4. Collection page text | Your top 5 collections 5. Product titles vs searches | GSC queries vs product names 6. Canonicals on filter URLs | View source on a filtered URL 7. Out-of-stock handling | Visit 3 sold-out products 8. Mobile Core Web Vitals | GSC > Core Web Vitals 9. Internal links to top collections | Homepage + menu + blog 10. Last year's seasonal URLs | Type /black-friday into your domain Bottom bar: "3+ problems = organic revenue left on the table" | Footer: Mehrooz Shafique · Permanent SEO | Banner: Comment "STORECHECK" for the audit sheet CTA BANNER (bottom, navy rounded box, white text, keyword in blue): Comment "STORECHECK" for 10-Point Store SEO Audit Sheet (Google Sheet with where-to-check notes) Footer on every frame: small circular headshot avatar + name tag 'Muhammad Mehrooz Shafique · Co-Founder, Permanent SEO' bottom-left; Permanent SEO 'P' logo (rising bar-chart + arrow mark) bottom-right. All text spelled exactly as written, sharp and legible on mobile; no extra words, no watermarks. | U6: Create a 1080x1350 Instagram post. Bold creator style: deep gradient background #345DF5 (top) to #191A46 (bottom), huge white Bebas Neue / Anton condensed headline, key words highlighted in #1566D7 highlight boxes or light-blue text, high contrast. HEADLINE (top, 2–3 lines, giant): "The 10-point store SEO audit. One hour. No tools you don't have." BODY (numbered points / simple visual): the 3–5 key points from this brief, shortened to max 8 words each: Single image, 1080x1350 (IG) and 1200x1500 (LinkedIn). Style: clean checklist infographic, dark navy background, white text, one accent colour (green ticks). Headline (top, bold condensed): THE 10-POINT STORE SEO AUDIT Sub-headline: One hour. Google Search Console + a browser. Numbered list in two columns, each item = check + where to find it: 1. Indexed vs not indexed | GSC > Pages 2. Top 20 queries | GSC > Performance > Queries 3. Homepage title tag | View source / browser tab 4. Collection page text | Your top 5 collections 5. Product titles vs searches | GSC queries vs product names 6. Canonicals on filter URLs | View source on a filtered URL 7. Out-of-stock handling | Visit 3 sold-out products 8. Mobile Core Web Vitals | GSC > Core Web Vitals 9. Internal links to top collections | Homepage + menu + blog 10. Last year's seasonal URLs | Type /black-friday into your domain Bottom bar: "3+ problems = organic revenue left on the table" | Footer: Mehrooz Shafique · Permanent SEO | Banner: Comment "STORECHECK" for the audit sheet BOTTOM BAR: Comment "STORECHECK" for 10-Point Store SEO Audit Sheet (Google Sheet with where-to-check notes) Footer on every frame: small circular headshot avatar + name tag 'Muhammad Mehrooz Shafique · Co-Founder, Permanent SEO' bottom-left; Permanent SEO 'P' logo (rising bar-chart + arrow mark) bottom-right (white versions). All text spelled exactly as written, sharp and legible on mobile; no extra words, no watermarks. | V6: STORECHECK | W6: 10-Point Store SEO Audit Sheet (Google Sheet with where-to-check notes) | X6: A store SEO audit doesn't need paid tools. Search Console + a browser + 1 hour: → Indexed vs not indexed → Top 20 queries → Collection page text → Filter canonicals → Out-of-stock pages → Mobile CWV → Last year's BFCM URLs #EcommerceSEO | Y6: Repost the Instagram caption + same visual | Z6: X post + image · Facebook image post | AG6: 08:30 / 18:30 | AH6: Planned
A7: 3 | B7: 46330 | C7: Wed | D7: 1 | E7: Nov 2026 | F7: E-commerce SEO Foundations + Black Friday / Cyber Monday SEO | G7: Myth-Busting | H7: REEL | I7: LinkedIn native vertical video | J7: Instagram Reel (9:16) | K7: Myth: delete your Black Friday page after the sale | L7: We don't delete Black Friday pages. We keep them. | M7: black friday landing page SEO | N7: evergreen black friday URL, seasonal landing page SEO, BFCM page SEO, should I delete black friday page | O7: Most stores delete their Black Friday page in December. Then rebuild it from scratch every November. That's the mistake, and it costs more every year. A page that has existed for years has history. Links from deal sites. Mentions. Clicks. Google has seen it before. A new URL every year starts at zero. Two weeks before the biggest sales weekend. What to do instead: → One permanent URL: /black-friday (no year in it) → After the sale, update the page: "Our next Black Friday sale is coming. Join the list." → Keep it in your footer or sitemap so it stays indexed → Refresh the content each October The page sleeps. The authority doesn't. Comment "EVERGREEN" and I'll send you the Evergreen Seasonal Page Template. #BlackFriday #EcommerceSEO #ShopifySEO #SeasonalSEO | P7: #BlackFriday #EcommerceSEO #ShopifySEO #SeasonalSEO | Q7: Don't delete your Black Friday page. → Keep one URL with no year in it → After the sale, switch it to "coming soon + join the list" → Keep it indexed → Refresh it every October The page sleeps. The authority doesn't. Share this with a store owner who rebuilds every year. Comment "EVERGREEN" for the Evergreen Seasonal Page Template. #blackfriday #blackfridaysale #ecommerceseo #shopifyseo #seotips #onlinestore #ecommercetips #cybermonday #shopifystore #smallbusiness #seasonalmarketing #woocommerce | R7: #blackfriday #blackfridaysale #ecommerceseo #shopifyseo #seotips #onlinestore #ecommercetips #cybermonday #shopifystore #smallbusiness #seasonalmarketing #woocommerce | S7: [0-2s] VO: We don't delete Black Friday pages. | ON-SCREEN: WE DON'T DELETE BLACK FRIDAY PAGES. | VISUAL: Bold white kinetic type on black, a page icon being dragged to a bin then stopped [2-4s] VO: We keep them. | ON-SCREEN: WE KEEP THEM. | VISUAL: Page icon snaps back, glows [4-7s] VO: Most stores do the same thing every December. | ON-SCREEN: MOST STORES, EVERY DECEMBER: | VISUAL: Calendar flips to December [7-9s] VO: Sale ends. | ON-SCREEN: SALE ENDS. | VISUAL: Price tag fades [9-10s] VO: Page deleted. | ON-SCREEN: PAGE DELETED. | VISUAL: 404 flashes [10-12s] VO: Rebuilt in November. | ON-SCREEN: REBUILT IN NOVEMBER. | VISUAL: Empty page skeleton [12-15s] VO: But a seasonal page needs three things. | ON-SCREEN: BUT IT NEEDS 3 THINGS | VISUAL: Three empty slots [15-18s] VO: One URL. No year in it. | ON-SCREEN: 1. ONE URL. NO YEAR. | VISUAL: /black-friday typed in a browser bar [18-21s] VO: A holding message after the sale. | ON-SCREEN: 2. A HOLDING MESSAGE | VISUAL: "Next sale coming. Join the list." [21-24s] VO: A refresh every October. | ON-SCREEN: 3. A REFRESH EVERY OCTOBER | VISUAL: Calendar to October, page updates [24-27s] VO: Without those three, every single year starts at zero. | ON-SCREEN: EVERY YEAR STARTS AT ZERO | VISUAL: Counter resets to 0 [27-29s] VO: The page sleeps. | ON-SCREEN: THE PAGE SLEEPS. | VISUAL: Page dims [29-32s] VO: The authority doesn't. | ON-SCREEN: THE AUTHORITY DOESN'T. | VISUAL: Page pulses; end card "Comment EVERGREEN" + @Mehrooz · Permanent SEO | T7: Same video as Instagram Reel (upload natively, 9:16, add captions). See Instagram prompt → | U7: Produce a 1080x1920 vertical reel, 25–35 s. Visual style: soft white studio background with subtle grid and soft corner shadows, mostly monochrome (black, grey, white) with ONE accent colour blue #1566D7; cinematic 3D objects (rocket, credit card, balance scale, puzzle pieces, magnifying glass, Google/Shopify-style app icons) that move in with motion blur; kinetic typography: bold geometric sans, one or two words per beat, key word in large grey/blue. Permanent SEO logo small at top-centre throughout. Voiceover: calm, deep, confident male narrator; measured pace (~130 words/min); a short pause between every line; no hype, no music drops over the voice; subtle minimal ambient bed + soft whoosh on text changes. BEATS: [0-2s] VO: We don't delete Black Friday pages. | ON-SCREEN: WE DON'T DELETE BLACK FRIDAY PAGES. | VISUAL: Bold white kinetic type on black, a page icon being dragged to a bin then stopped [2-4s] VO: We keep them. | ON-SCREEN: WE KEEP THEM. | VISUAL: Page icon snaps back, glows [4-7s] VO: Most stores do the same thing every December. | ON-SCREEN: MOST STORES, EVERY DECEMBER: | VISUAL: Calendar flips to December [7-9s] VO: Sale ends. | ON-SCREEN: SALE ENDS. | VISUAL: Price tag fades [9-10s] VO: Page deleted. | ON-SCREEN: PAGE DELETED. | VISUAL: 404 flashes [10-12s] VO: Rebuilt in November. | ON-SCREEN: REBUILT IN NOVEMBER. | VISUAL: Empty page skeleton [12-15s] VO: But a seasonal page needs three things. | ON-SCREEN: BUT IT NEEDS 3 THINGS | VISUAL: Three empty slots [15-18s] VO: One URL. No year in it. | ON-SCREEN: 1. ONE URL. NO YEAR. | VISUAL: /black-friday typed in a browser bar [18-21s] VO: A holding message after the sale. | ON-SCREEN: 2. A HOLDING MESSAGE | VISUAL: "Next sale coming. Join the list." [21-24s] VO: A refresh every October. | ON-SCREEN: 3. A REFRESH EVERY OCTOBER | VISUAL: Calendar to October, page updates [24-27s] VO: Without those three, every single year starts at zero. | ON-SCREEN: EVERY YEAR STARTS AT ZERO | VISUAL: Counter resets to 0 [27-29s] VO: The page sleeps. | ON-SCREEN: THE PAGE SLEEPS. | VISUAL: Page dims [29-32s] VO: The authority doesn't. | ON-SCREEN: THE AUTHORITY DOESN'T. | VISUAL: Page pulses; end card "Comment EVERGREEN" + @Mehrooz · Permanent SEO Final 3 s: dark/navy end card with Permanent SEO logo, 'SEO for E-commerce Brands' and 'Comment "EVERGREEN"'. Burned-in captions. All text spelled exactly as written, sharp and legible on mobile; no extra words, no watermarks. | V7: EVERGREEN | W7: Evergreen Seasonal Page Template (Black Friday / Cyber Monday page outline + off-season copy) | X7: Stop deleting your Black Friday page in December. One URL. No year in it. Holding message after the sale. Refresh in October. A new URL every year starts at zero. The page sleeps. The authority doesn't. #BlackFriday #EcommerceSEO | Y7: Repost the Instagram caption + same visual as Facebook Reel | Z7: YouTube Shorts · Facebook Reels · X video | AA7: Black Friday Landing Page SEO: Why You Should Never Delete It | AB7: Black Friday landing page SEO in 30 seconds: keep one permanent URL, switch it to a holding message after the sale, and refresh it every October so it keeps its authority. #Shorts | AC7: black friday landing page SEO, black friday SEO, seasonal landing page, ecommerce SEO, shopify SEO, BFCM SEO, evergreen URL, cyber monday SEO, online store SEO, Permanent SEO | AG7: 12:00 / 19:00 | AH7: Planned
A8: 4 | B8: 46331 | C8: Thu | D8: 1 | E8: Nov 2026 | F8: E-commerce SEO Foundations + Black Friday / Cyber Monday SEO | G8: Explainer | H8: LONG_VIDEO | I8: LinkedIn Long Video (16:9) | J8: Instagram Reel (30–45 s vertical cut) | K8: Google Search Console for store owners: the 4 reports that matter | L8: You don't need all of Search Console. You need 4 reports. | M8: google search console for ecommerce | N8: Search Console for Shopify, GSC performance report, GSC pages report, Search Console tutorial for store owners | O8: Most store owners open Google Search Console once, see 40 menus, and close it. You don't need all of it. You need 4 reports. 1. Performance → Queries What people actually type before they find you. Sort by impressions. Look for buying queries with low clicks. 2. Performance → Pages Which product and collection pages earn clicks. Compare this month vs last year to see seasonal patterns. 3. Pages (Indexing) Which URLs Google refuses to index, and why. "Crawled, currently not indexed" on a collection page is a warning sign. 4. Core Web Vitals Mobile first. Poor URLs here will hurt you most when traffic peaks. 15 minutes a week across these 4 reports will tell you more about your store than most monthly reports. The video walks through each one. Comment "CONSOLE" and I'll send you the Search Console Weekly Routine for Store Owners. #GoogleSearchConsole #EcommerceSEO #ShopifySEO #SEO | P8: #GoogleSearchConsole #EcommerceSEO #ShopifySEO #SEO | Q8: Search Console has 40 menus. Store owners need 4. → Performance: Queries → Performance: Pages → Pages (Indexing) → Core Web Vitals 15 minutes a week. That's it. Start with queries that get impressions but no clicks. Those are usually the quickest wins. Save this before your next login. Comment "CONSOLE" for the Search Console Weekly Routine for Store Owners. #googlesearchconsole #ecommerceseo #seotips #shopifyseo #onlinestore #storeowner #seoforbeginners #woocommerce #ecommercetips #shopifytips #technicalseo #digitalmarketing | R8: #googlesearchconsole #ecommerceseo #seotips #shopifyseo #onlinestore #storeowner #seoforbeginners #woocommerce #ecommercetips #shopifytips #technicalseo #digitalmarketing | S8: Scene 1 [0-10s] VO: "Okay. Search Console. Performance, Pages, Links, Experience, Enhancements... yeah, I'll look at this later." Close tab. | VISUAL: Animated store owner at laptop, GSC sidebar menus multiplying, tab closes Scene 2 [10-20s] VO: "Let's be honest. The data on why your store isn't growing is already in there. You just don't know which part to read." | VISUAL: Magnifier over a blurred dashboard Scene 3 [20-30s] VO: "So you guess. More products. More ads. More blog posts. And the real problems sit there untouched." | VISUAL: Three icons stacking, a red warning blinking underneath Scene 4 [30-38s] VO: "Here's how we use it at Permanent SEO. Four reports. Fifteen minutes a week." | VISUAL: Logo, then four tiles Scene 5 [38-50s] VO: "One. Performance, queries. Sort by impressions. Find buying searches where you show up but nobody clicks. Those titles need work." | VISUAL: Query table, high-impression low-CTR rows highlighted Scene 6 [50-62s] VO: "Two. Performance, pages. See which collections and products earn clicks. Compare to last year to spot seasonal pages." | VISUAL: Date compare toggle, line chart rising in November Scene 7 [62-74s] VO: "Three. The Pages report. If a collection says crawled, currently not indexed, Google doesn't think it's worth showing." | VISUAL: Indexing reasons list, collection URL flagged Scene 8 [74-84s] VO: "Four. Core Web Vitals, on mobile. Fix poor URLs before peak traffic, not during it." | VISUAL: Poor / needs improvement / good bars Scene 9 [84-92s] VO: "That's the result we look for: [CLIENT RESULT: what changed after weekly GSC reviews]." | VISUAL: Placeholder results card Scene 10 [92-105s] VO: "Comment CONSOLE and I'll send you the weekly routine. Or book a free e-commerce SEO audit with Permanent SEO." | VISUAL: End card, keyword, Mehrooz name + Permanent SEO | T8: Produce a 1920x1080 motion-graphics explainer, 60–120 s. Visual style: bright white/very light blue #F4F7FD canvas, floating UI mockups (Google results, Search Console charts, product pages, ChatGPT answers), kinetic typography where key words turn blue #1566D7, smooth parallax and soft shadows, occasional full-bleed blue #1566D7 scene with one giant word. Voiceover: calm, deep, confident male narrator; measured pace (~130 words/min); a short pause between every line; no hype, no music drops over the voice; subtle minimal ambient bed + soft whoosh on text changes. SCRIPT & SCENES: Scene 1 [0-10s] VO: "Okay. Search Console. Performance, Pages, Links, Experience, Enhancements... yeah, I'll look at this later." Close tab. | VISUAL: Animated store owner at laptop, GSC sidebar menus multiplying, tab closes Scene 2 [10-20s] VO: "Let's be honest. The data on why your store isn't growing is already in there. You just don't know which part to read." | VISUAL: Magnifier over a blurred dashboard Scene 3 [20-30s] VO: "So you guess. More products. More ads. More blog posts. And the real problems sit there untouched." | VISUAL: Three icons stacking, a red warning blinking underneath Scene 4 [30-38s] VO: "Here's how we use it at Permanent SEO. Four reports. Fifteen minutes a week." | VISUAL: Logo, then four tiles Scene 5 [38-50s] VO: "One. Performance, queries. Sort by impressions. Find buying searches where you show up but nobody clicks. Those titles need work." | VISUAL: Query table, high-impression low-CTR rows highlighted Scene 6 [50-62s] VO: "Two. Performance, pages. See which collections and products earn clicks. Compare to last year to spot seasonal pages." | VISUAL: Date compare toggle, line chart rising in November Scene 7 [62-74s] VO: "Three. The Pages report. If a collection says crawled, currently not indexed, Google doesn't think it's worth showing." | VISUAL: Indexing reasons list, collection URL flagged Scene 8 [74-84s] VO: "Four. Core Web Vitals, on mobile. Fix poor URLs before peak traffic, not during it." | VISUAL: Poor / needs improvement / good bars Scene 9 [84-92s] VO: "That's the result we look for: [CLIENT RESULT: what changed after weekly GSC reviews]." | VISUAL: Placeholder results card Scene 10 [92-105s] VO: "Comment CONSOLE and I'll send you the weekly routine. Or book a free e-commerce SEO audit with Permanent SEO." | VISUAL: End card, keyword, Mehrooz name + Permanent SEO End card: Permanent SEO logo + 'Comment "CONSOLE"' + 'Muhammad Mehrooz Shafique · Co-Founder, Permanent SEO'. Burn in captions. All text spelled exactly as written, sharp and legible on mobile; no extra words, no watermarks. | U8: Produce a 1080x1920 vertical reel, 25–35 s. Visual style: soft white studio background with subtle grid and soft corner shadows, mostly monochrome (black, grey, white) with ONE accent colour blue #1566D7; cinematic 3D objects (rocket, credit card, balance scale, puzzle pieces, magnifying glass, Google/Shopify-style app icons) that move in with motion blur; kinetic typography: bold geometric sans, one or two words per beat, key word in large grey/blue. Permanent SEO logo small at top-centre throughout. Voiceover: calm, deep, confident male narrator; measured pace (~130 words/min); a short pause between every line; no hype, no music drops over the voice; subtle minimal ambient bed + soft whoosh on text changes. BEATS: Vertical 30–45 s cut of the long video: keep the opener, the problem line, the 3–4 steps as one-word beats and the CTA. Source script: Scene 1 [0-10s] VO: "Okay. Search Console. Performance, Pages, Links, Experience, Enhancements... yeah, I'll look at this later." Close tab. | VISUAL: Animated store owner at laptop, GSC sidebar menus multiplying, tab closes Scene 2 [10-20s] VO: "Let's be honest. The data on why your store isn't growing is already in there. You just don't know which part to read." | VISUAL: Magnifier over a blurred dashboard Scene 3 [20-30s] VO: "So you guess. More products. More ads. More blog posts. And the real problems sit there untouched." | VISUAL: Three icons stacking, a red warning blinking underneath Scene 4 [30-38s] VO: "Here's how we use it at Permanent SEO. Four reports. Fifteen minutes a week." | VISUAL: Logo, then four tiles Scene 5 [38-50s] VO: "One. Performance, queries. Sort by impressions. Find buying searches where you show up but nobody clicks. Those titles need work." | VISUAL: Query table, high-impression low-CTR rows highlighted Scene 6 [50-62s] VO: "Two. Performance, pages. See which collections and products earn clicks. Compare to last year to spot seasonal pages." | VISUAL: Date compare toggle, line chart rising in November Scene 7 [62-74s] VO: "Three. The Pages report. If a collection says crawled, currently not indexed, Google doesn't think it's worth showing." | VISUAL: Indexing reasons list, collection URL flagged Scene 8 [74-84s] VO: "Four. Core Web Vitals, on mobile. Fix poor URLs before peak traffic, not during it." | VISUAL: Poor / needs improvement / good bars Scene 9 [84-92s] VO: "That's the result we look for: [CLIENT RESULT: what changed after weekly GSC reviews]." | VISUAL: Placeholder results card Scene 10 [92-105s] VO: "Comment CONSOLE and I'll send you the weekly routine. Or book a free e-commerce SEO audit with Permanent SEO." | VISUAL: End card, keyword, Mehrooz name + Permanent SEO Final 3 s: dark/navy end card with Permanent SEO logo, 'SEO for E-commerce Brands' and 'Comment "CONSOLE"'. Burned-in captions. All text spelled exactly as written, sharp and legible on mobile; no extra words, no watermarks. | V8: CONSOLE | W8: Search Console Weekly Routine for Store Owners (15-minute checklist PDF) | X8: Store owners don't need all of Google Search Console. Just 4 reports: 1. Performance → Queries 2. Performance → Pages 3. Pages (Indexing) 4. Core Web Vitals (mobile) 15 minutes a week. #EcommerceSEO | Y8: Repost the Instagram caption + same visual (upload 16:9 natively) | Z8: YouTube long video · Facebook native video · X clip (first 45 s) | AA8: Google Search Console for Ecommerce: The Only 4 Reports You Need | AB8: Google Search Console for ecommerce explained for store owners. Mehrooz Shafique from Permanent SEO walks through the 4 reports that show why your store isn't growing, and a 15-minute weekly routine to use them. | AC8: google search console for ecommerce, search console tutorial, shopify SEO, ecommerce SEO, GSC performance report, GSC pages report, core web vitals, store owner SEO, woocommerce SEO, Permanent SEO | AG8: 08:30 / 18:30 | AH8: Planned
A9: 5 | B9: 46332 | C9: Fri | D9: 1 | E9: Nov 2026 | F9: E-commerce SEO Foundations + Black Friday / Cyber Monday SEO | G9: Proof & Freebie | H9: POST | I9: LinkedIn Post (detailed image) | J9: Instagram Post (single image) | K9: Free guide preview: the Black Friday SEO Playbook for stores | L9: The Black Friday SEO Playbook. 7 chapters. Free. | M9: black friday SEO checklist | N9: BFCM SEO, Black Friday SEO tips, cyber monday SEO, holiday ecommerce SEO | O9: Black Friday is 27 November. Cyber Monday is 30 November. Three weeks is enough time to fix the SEO basics. It's not enough to start from nothing. So I put everything we check before peak season into one playbook: 1. The permanent BFCM URL strategy 2. Search Console checks for the next 21 days 3. Category vs product page intent for deal searches 4. Internal linking to holiday collections 5. Merchant Center free listings setup 6. Out-of-stock rules for sale week 7. Speed fixes before traffic peaks No theory. Each chapter ends with a short checklist you can hand to whoever runs your store. I'm giving it away free this month. Comment "PLAYBOOK" and I'll send you the Black Friday SEO Playbook. #BlackFriday #CyberMonday #EcommerceSEO #ShopifySEO | P9: #BlackFriday #CyberMonday #EcommerceSEO #ShopifySEO | Q9: The Black Friday SEO Playbook. Free. 1. Permanent BFCM URLs 2. Search Console checks 3. Category vs product intent 4. Internal links to holiday collections 5. Merchant Center free listings 6. Out-of-stock rules 7. Speed before peak Each chapter ends with a short checklist you can hand to your team. Three weeks left. Save this. Comment "PLAYBOOK" for the Black Friday SEO Playbook. #blackfriday #cybermonday #bfcm #ecommerceseo #shopifyseo #seotips #onlinestore #blackfridaysale #ecommercetips #shopifystore #woocommerce #holidaymarketing #smallbusiness | R9: #blackfriday #cybermonday #bfcm #ecommerceseo #shopifyseo #seotips #onlinestore #blackfridaysale #ecommercetips #shopifystore #woocommerce #holidaymarketing #smallbusiness | S9: Single image "guide preview", 1080x1350. Layout: left 55% = mock 3D cover of an ebook titled "THE BLACK FRIDAY SEO PLAYBOOK" with sub-title "For Shopify & WooCommerce stores · 2026 edition" and author line "Muhammad Mehrooz Shafique · Permanent SEO". Right 45% = "INSIDE:" with numbered chapters: 01 The permanent BFCM URL strategy 02 Search Console: 21-day checks 03 Category vs product intent 04 Internal links to holiday collections 05 Merchant Center free listings 06 Out-of-stock rules for sale week 07 Speed fixes before peak traffic Top corner tag: "Black Friday 27 Nov · Cyber Monday 30 Nov". Bottom full-width banner, bright accent colour: Comment "PLAYBOOK" for free access. | T9: Create a 1080x1350 LinkedIn infographic. Clean premium editorial style: off-white #F4F7FD background, primary blue #1566D7 accents, navy #191A46 text, headlines in Bebas Neue (bold condensed, all caps), body in Inter; generous margins, faint grid lines, crisp vector icons, no stock-photo clutter. HEADLINE: "The Black Friday SEO Playbook. 7 chapters. Free." SUBHEAD: "Free guide preview: the Black Friday SEO Playbook for stores" MAIN VISUAL: the layout described below containing exactly: Single image "guide preview", 1080x1350. Layout: left 55% = mock 3D cover of an ebook titled "THE BLACK FRIDAY SEO PLAYBOOK" with sub-title "For Shopify & WooCommerce stores · 2026 edition" and author line "Muhammad Mehrooz Shafique · Permanent SEO". Right 45% = "INSIDE:" with numbered chapters: 01 The permanent BFCM URL strategy 02 Search Console: 21-day checks 03 Category vs product intent 04 Internal links to holiday collections 05 Merchant Center free listings 06 Out-of-stock rules for sale week 07 Speed fixes before peak traffic Top corner tag: "Black Friday 27 Nov · Cyber Monday 30 Nov". Bottom full-width banner, bright accent colour: Comment "PLAYBOOK" for free access. CTA BANNER (bottom, navy rounded box, white text, keyword in blue): Comment "PLAYBOOK" for Black Friday SEO Playbook (7-chapter PDF with checklists) Footer on every frame: small circular headshot avatar + name tag 'Muhammad Mehrooz Shafique · Co-Founder, Permanent SEO' bottom-left; Permanent SEO 'P' logo (rising bar-chart + arrow mark) bottom-right. All text spelled exactly as written, sharp and legible on mobile; no extra words, no watermarks. | U9: Create a 1080x1350 Instagram post. Bold creator style: deep gradient background #345DF5 (top) to #191A46 (bottom), huge white Bebas Neue / Anton condensed headline, key words highlighted in #1566D7 highlight boxes or light-blue text, high contrast. HEADLINE (top, 2–3 lines, giant): "The Black Friday SEO Playbook. 7 chapters. Free." BODY (numbered points / simple visual): the 3–5 key points from this brief, shortened to max 8 words each: Single image "guide preview", 1080x1350. Layout: left 55% = mock 3D cover of an ebook titled "THE BLACK FRIDAY SEO PLAYBOOK" with sub-title "For Shopify & WooCommerce stores · 2026 edition" and author line "Muhammad Mehrooz Shafique · Permanent SEO". Right 45% = "INSIDE:" with numbered chapters: 01 The permanent BFCM URL strategy 02 Search Console: 21-day checks 03 Category vs product intent 04 Internal links to holiday collections 05 Merchant Center free listings 06 Out-of-stock rules for sale week 07 Speed fixes before peak traffic Top corner tag: "Black Friday 27 Nov · Cyber Monday 30 Nov". Bottom full-width banner, bright accent colour: Comment "PLAYBOOK" for free access. BOTTOM BAR: Comment "PLAYBOOK" for Black Friday SEO Playbook (7-chapter PDF with checklists) Footer on every frame: small circular headshot avatar + name tag 'Muhammad Mehrooz Shafique · Co-Founder, Permanent SEO' bottom-left; Permanent SEO 'P' logo (rising bar-chart + arrow mark) bottom-right (white versions). All text spelled exactly as written, sharp and legible on mobile; no extra words, no watermarks. | V9: PLAYBOOK | W9: Black Friday SEO Playbook (7-chapter PDF with checklists) | X9: Black Friday is 27 Nov. Three weeks left. I wrote a free Black Friday SEO Playbook: permanent URLs, GSC checks, intent, internal links, Merchant Center, out-of-stock rules, speed. Reply "PLAYBOOK" and I'll send it. #BlackFriday #EcommerceSEO | Y9: Repost the Instagram caption + same visual | Z9: X post + image · Facebook image post | AG9: 09:00 / 12:30 | AH9: Planned
A10: 6 | B10: 46335 | C10: Mon | D10: 2 | E10: Nov 2026 | F10: E-commerce SEO Foundations + Black Friday / Cyber Monday SEO | G10: Educate | H10: SLIDE | I10: LinkedIn Slide Post (PDF carousel) | J10: Instagram Slide Post (carousel) | K10: Product vs category page intent: which page should rank for what | L10: Your product page is ranking for the wrong search. Here's why. | M10: category page vs product page SEO | N10: search intent ecommerce, collection page SEO, product page SEO, keyword mapping for ecommerce | O10: "Why is my product page ranking for a broad search and not converting?" Because it's the wrong page for that search. Google reads intent first. → "running shoes" = I want to compare options → category page → "nike pegasus 41 mens size 10" = I know what I want → product page → "best running shoes for flat feet" = I want advice → guide that links to a category → "running shoes black friday" = I want deals → seasonal collection When you force a product page onto a broad search, two things happen. It struggles to rank. And when it does, people bounce because they wanted choice. The fix is a simple keyword map: one search intent, one page type, one URL. The carousel walks through how to build it for your store. Comment "INTENTMAP" and I'll send you the E-commerce Keyword-to-Page Intent Map. #EcommerceSEO #SearchIntent #ShopifySEO #KeywordResearch | P10: #EcommerceSEO #SearchIntent #ShopifySEO #KeywordResearch | Q10: Product page or category page? Google decides by intent. → "running shoes" = category → "pegasus 41 size 10" = product → "best shoes for flat feet" = guide → "running shoes black friday" = seasonal collection One intent. One page type. One URL. Save this before you write your next title tag. Comment "INTENTMAP" for the E-commerce Keyword-to-Page Intent Map. #searchintent #ecommerceseo #keywordresearch #shopifyseo #seotips #onlinestore #productpage #woocommerce #ecommercetips #seostrategy #shopifystore #contentstrategy | R10: #searchintent #ecommerceseo #keywordresearch #shopifyseo #seotips #onlinestore #productpage #woocommerce #ecommercetips #seostrategy #shopifystore #contentstrategy | S10: Slide 1: Your product page is ranking for the wrong search. | Product vs category page intent, explained. Slide 2: Google reads intent first | Before your title, your copy or your links. What does the searcher want to do next? Slide 3: Broad search = compare | "running shoes" → category page. People want choice, filters, prices. Slide 4: Specific search = buy | "nike pegasus 41 mens size 10" → product page. They know exactly what they want. Slide 5: Question search = learn | "best running shoes for flat feet" → guide or buying page that links to the category. Slide 6: Seasonal search = deals | "running shoes black friday" → seasonal collection on a permanent URL. Slide 7: What goes wrong | A product page forced onto a broad search ranks poorly and converts worse. Slide 8: Build the map | Column 1: keyword. Column 2: intent. Column 3: page type. Column 4: URL. One URL per intent. Slide 9: Check it in Search Console | Performance → Pages → pick a product → Queries. Broad queries here = a missing category page. Slide 10: Comment "INTENTMAP" | Get the E-commerce Keyword-to-Page Intent Map. Follow Mehrooz for more store SEO. | T10: Design a 10-slide LinkedIn PDF carousel, 1080x1350 each. Clean premium editorial style: off-white #F4F7FD background, primary blue #1566D7 accents, navy #191A46 text, headlines in Bebas Neue (bold condensed, all caps), body in Inter; generous margins, faint grid lines, crisp vector icons, no stock-photo clutter. Cover slide like a premium guide cover: giant two-tone headline (key word in blue), small illustration/UI mockup, numbered contents list. Inner slides: big slide number in blue, Bebas Neue title, short Inter body, one diagram/mockup/checklist per slide. Last slide: navy CTA banner with download icon. SLIDE CONTENT: Slide 1: Your product page is ranking for the wrong search. | Product vs category page intent, explained. Slide 2: Google reads intent first | Before your title, your copy or your links. What does the searcher want to do next? Slide 3: Broad search = compare | "running shoes" → category page. People want choice, filters, prices. Slide 4: Specific search = buy | "nike pegasus 41 mens size 10" → product page. They know exactly what they want. Slide 5: Question search = learn | "best running shoes for flat feet" → guide or buying page that links to the category. Slide 6: Seasonal search = deals | "running shoes black friday" → seasonal collection on a permanent URL. Slide 7: What goes wrong | A product page forced onto a broad search ranks poorly and converts worse. Slide 8: Build the map | Column 1: keyword. Column 2: intent. Column 3: page type. Column 4: URL. One URL per intent. Slide 9: Check it in Search Console | Performance → Pages → pick a product → Queries. Broad queries here = a missing category page. Slide 10: Comment "INTENTMAP" | Get the E-commerce Keyword-to-Page Intent Map. Follow Mehrooz for more store SEO. Footer on every frame: small circular headshot avatar + name tag 'Muhammad Mehrooz Shafique · Co-Founder, Permanent SEO' bottom-left; Permanent SEO 'P' logo (rising bar-chart + arrow mark) bottom-right. All text spelled exactly as written, sharp and legible on mobile; no extra words, no watermarks. | U10: Design a 10-slide Instagram carousel, 1080x1350 each. Bold creator style: deep gradient background #345DF5 (top) to #191A46 (bottom), huge white Bebas Neue / Anton condensed headline, key words highlighted in #1566D7 highlight boxes or light-blue text, high contrast. Slide 1 = scroll-stopping cover with giant condensed headline and a 'swipe →' cue; inner slides alternate navy and white backgrounds, big blue slide number, max 25 words, one icon or mini-diagram each; last slide = CTA with comment keyword in a blue pill. SLIDE CONTENT: Slide 1: Your product page is ranking for the wrong search. | Product vs category page intent, explained. Slide 2: Google reads intent first | Before your title, your copy or your links. What does the searcher want to do next? Slide 3: Broad search = compare | "running shoes" → category page. People want choice, filters, prices. Slide 4: Specific search = buy | "nike pegasus 41 mens size 10" → product page. They know exactly what they want. Slide 5: Question search = learn | "best running shoes for flat feet" → guide or buying page that links to the category. Slide 6: Seasonal search = deals | "running shoes black friday" → seasonal collection on a permanent URL. Slide 7: What goes wrong | A product page forced onto a broad search ranks poorly and converts worse. Slide 8: Build the map | Column 1: keyword. Column 2: intent. Column 3: page type. Column 4: URL. One URL per intent. Slide 9: Check it in Search Console | Performance → Pages → pick a product → Queries. Broad queries here = a missing category page. Slide 10: Comment "INTENTMAP" | Get the E-commerce Keyword-to-Page Intent Map. Follow Mehrooz for more store SEO. Footer on every frame: small circular headshot avatar + name tag 'Muhammad Mehrooz Shafique · Co-Founder, Permanent SEO' bottom-left; Permanent SEO 'P' logo (rising bar-chart + arrow mark) bottom-right. All text spelled exactly as written, sharp and legible on mobile; no extra words, no watermarks. | V10: INTENTMAP | W10: E-commerce Keyword-to-Page Intent Map (Google Sheet template with examples) | X10: Your product page might be ranking for the wrong search. Google reads intent before anything else. Here's how to match search type to page type in an online store. --- Broad search = compare. "running shoes" → category page. People want choice, filters and prices. --- Specific search = buy. "nike pegasus 41 mens size 10" → product page. --- Question search = learn. "best running shoes for flat feet" → guide that links into the category. Seasonal search = deals. "running shoes black friday" → seasonal collection on a permanent URL. --- Quick check: Search Console → Performance → Pages → open a product → Queries. Broad queries landing on a product page usually means a missing category page. --- Build a 4-column map: keyword, intent, page type, URL. One intent. One page. One URL. #EcommerceSEO | Y10: Repost the Instagram caption + same visual | Z10: X thread · Facebook carousel · Reddit text post | AD10: r/shopify | AE10: How to decide if a keyword should go to a product page or a collection page | AF10: A common issue I see in Shopify stores: product pages ranking (badly) for broad searches that should go to a collection. A simple way to decide is to look at what the searcher wants to do next. - Broad terms like "running shoes" usually mean they want to compare. Collection page. - Specific terms with model, size or colour mean they know what they want. Product page. - Questions like "best X for Y" mean they want advice. A guide or buying page that links to the collection. - Seasonal terms like "X black friday" mean they want deals. A seasonal collection that lives on the same URL every year. Fastest way to check your own store: Search Console, Performance, Pages, click a product URL, then switch to Queries. If you see broad category-style queries there, you probably need a stronger collection page for them. Once you know, map it in a sheet: keyword, intent, page type, URL. One intent per URL. How do you all handle this when a product is basically the whole category, like a single-product store? | AG10: 08:30 / 12:30 | AH10: Planned
A11: 7 | B11: 46336 | C11: Tue | D11: 2 | E11: Nov 2026 | F11: E-commerce SEO Foundations + Black Friday / Cyber Monday SEO | G11: Data & Insight | H11: POST | I11: LinkedIn Post (detailed image) | J11: Instagram Post (single image) | K11: Yearly vs permanent BFCM URLs: a side-by-side comparison | L11: /black-friday-2026 vs /black-friday. Only one keeps its rankings. | M11: black friday URL structure SEO | N11: seasonal URL SEO, black friday page URL, permanent seasonal URL, BFCM landing page | O11: Two ways stores build their Black Friday page: Option A: /black-friday-2026 Option B: /black-friday They look almost the same. They behave very differently in Google. With a yearly URL: ❌ Every year is a brand new page ❌ Last year's links point to a dead or redirected URL ❌ Google has no history with it ❌ You rebuild internal links every November With a permanent URL: ✅ Links and history build year after year ✅ It can rank before the sale even starts ✅ One page to update, not one to create ✅ Off-season, it collects email sign-ups If you already have yearly URLs, don't panic. 301 redirect the old ones to one permanent URL and update your internal links. The table in the image shows the full comparison. Comment "ONEURL" and I'll send you the Seasonal URL Migration Checklist. #BlackFriday #EcommerceSEO #TechnicalSEO #ShopifySEO | P11: #BlackFriday #EcommerceSEO #TechnicalSEO #ShopifySEO | Q11: /black-friday-2026 vs /black-friday Yearly URL: ❌ New page every year ❌ Last year's links lost ❌ No history Permanent URL: ✅ Builds links every year ✅ Ranks before the sale starts ✅ Collects emails off-season Already have yearly URLs? 301 them to one permanent page and update your internal links. Save this before you build this year's page. Comment "ONEURL" for the Seasonal URL Migration Checklist. #blackfriday #ecommerceseo #technicalseo #shopifyseo #seotips #onlinestore #bfcm #cybermonday #woocommerce #ecommercetips #shopifystore #urlstructure | R11: #blackfriday #ecommerceseo #technicalseo #shopifyseo #seotips #onlinestore #bfcm #cybermonday #woocommerce #ecommercetips #shopifystore #urlstructure | S11: Single image, comparison table, 1080x1350. Headline: YEARLY URL vs PERMANENT URL. Sub-headline: Which Black Friday page keeps its rankings? Two column headers styled as browser bars: left "yoursite.com/black-friday-2026" (red tint), right "yoursite.com/black-friday" (green tint). Table rows (row label | yearly | permanent): Page age | Starts at zero every year | Grows every year Backlinks | Lost or redirected | Kept and growing Ranking before sale | Unlikely | Possible Internal links | Rebuilt each November | Set once Off-season use | Deleted or 404 | Email sign-up / "next sale" page Work each year | Build a new page | Update one page Bottom note box: "Already have yearly URLs? 301 redirect them to one permanent URL." Footer: Mehrooz Shafique · Permanent SEO | Banner: Comment "ONEURL" for the migration checklist | T11: Create a 1080x1350 LinkedIn infographic. Clean premium editorial style: off-white #F4F7FD background, primary blue #1566D7 accents, navy #191A46 text, headlines in Bebas Neue (bold condensed, all caps), body in Inter; generous margins, faint grid lines, crisp vector icons, no stock-photo clutter. HEADLINE: "/black-friday-2026 vs /black-friday. Only one keeps its rankings." SUBHEAD: "Yearly vs permanent BFCM URLs: a side-by-side comparison" MAIN VISUAL: the layout described below containing exactly: Single image, comparison table, 1080x1350. Headline: YEARLY URL vs PERMANENT URL. Sub-headline: Which Black Friday page keeps its rankings? Two column headers styled as browser bars: left "yoursite.com/black-friday-2026" (red tint), right "yoursite.com/black-friday" (green tint). Table rows (row label | yearly | permanent): Page age | Starts at zero every year | Grows every year Backlinks | Lost or redirected | Kept and growing Ranking before sale | Unlikely | Possible Internal links | Rebuilt each November | Set once Off-season use | Deleted or 404 | Email sign-up / "next sale" page Work each year | Build a new page | Update one page Bottom note box: "Already have yearly URLs? 301 redirect them to one permanent URL." Footer: Mehrooz Shafique · Permanent SEO | Banner: Comment "ONEURL" for the migration checklist CTA BANNER (bottom, navy rounded box, white text, keyword in blue): Comment "ONEURL" for Seasonal URL Migration Checklist (yearly-to-permanent redirect steps, PDF) Footer on every frame: small circular headshot avatar + name tag 'Muhammad Mehrooz Shafique · Co-Founder, Permanent SEO' bottom-left; Permanent SEO 'P' logo (rising bar-chart + arrow mark) bottom-right. All text spelled exactly as written, sharp and legible on mobile; no extra words, no watermarks. | U11: Create a 1080x1350 Instagram post. Bold creator style: deep gradient background #345DF5 (top) to #191A46 (bottom), huge white Bebas Neue / Anton condensed headline, key words highlighted in #1566D7 highlight boxes or light-blue text, high contrast. HEADLINE (top, 2–3 lines, giant): "/black-friday-2026 vs /black-friday. Only one keeps its rankings." BODY (numbered points / simple visual): the 3–5 key points from this brief, shortened to max 8 words each: Single image, comparison table, 1080x1350. Headline: YEARLY URL vs PERMANENT URL. Sub-headline: Which Black Friday page keeps its rankings? Two column headers styled as browser bars: left "yoursite.com/black-friday-2026" (red tint), right "yoursite.com/black-friday" (green tint). Table rows (row label | yearly | permanent): Page age | Starts at zero every year | Grows every year Backlinks | Lost or redirected | Kept and growing Ranking before sale | Unlikely | Possible Internal links | Rebuilt each November | Set once Off-season use | Deleted or 404 | Email sign-up / "next sale" page Work each year | Build a new page | Update one page Bottom note box: "Already have yearly URLs? 301 redirect them to one permanent URL." Footer: Mehrooz Shafique · Permanent SEO | Banner: Comment "ONEURL" for the migration checklist BOTTOM BAR: Comment "ONEURL" for Seasonal URL Migration Checklist (yearly-to-permanent redirect steps, PDF) Footer on every frame: small circular headshot avatar + name tag 'Muhammad Mehrooz Shafique · Co-Founder, Permanent SEO' bottom-left; Permanent SEO 'P' logo (rising bar-chart + arrow mark) bottom-right (white versions). All text spelled exactly as written, sharp and legible on mobile; no extra words, no watermarks. | V11: ONEURL | W11: Seasonal URL Migration Checklist (yearly-to-permanent redirect steps, PDF) | X11: /black-friday-2026 starts at zero every year. /black-friday builds links and history every year. Already have yearly URLs? 301 them to one permanent page and update internal links. #BlackFriday #SEO | Y11: Repost the Instagram caption + same visual | Z11: X post + image · Facebook image post | AG11: 08:30 / 18:30 | AH11: Planned
A12: 8 | B12: 46337 | C12: Wed | D12: 2 | E12: Nov 2026 | F12: E-commerce SEO Foundations + Black Friday / Cyber Monday SEO | G12: Myth-Busting | H12: REEL | I12: LinkedIn native vertical video | J12: Instagram Reel (9:16) | K12: Myth: remove out-of-stock products from your store | L12: We don't delete sold-out products. We keep the page working. | M12: out of stock products SEO | N12: sold out product page SEO, discontinued products SEO, Shopify out of stock SEO, 404 vs 301 ecommerce | O12: Sale week is when products sell out fastest. And it's when most stores make this mistake: they delete or hide the product. That URL might have taken months to rank. It might have links from reviews and gift guides. Delete it and all of that turns into a 404. What we do instead: → Temporarily out of stock: keep the page live, show "back soon", add a restock email sign-up and link to similar products → Permanently discontinued with a close replacement: 301 redirect to that replacement or the parent category → Discontinued with no replacement and no links: let it 404 or 410 The rule is simple. Ask what the searcher should see next. Sold out is a stock problem. Don't turn it into an SEO problem. Comment "RESTOCK" and I'll send you the Out-of-Stock Decision Tree. #EcommerceSEO #ShopifySEO #TechnicalSEO #BlackFriday | P12: #EcommerceSEO #ShopifySEO #TechnicalSEO #BlackFriday | Q12: Sold out? Don't delete the page. → Back soon: keep it live, add restock alerts, link alternatives → Gone with a replacement: 301 to it → Gone, no links, no replacement: let it 404 Sold out is a stock problem. Don't make it an SEO problem. Ask one question: what should the searcher see next? Save this for sale week. Comment "RESTOCK" for the Out-of-Stock Decision Tree. #ecommerceseo #shopifyseo #outofstock #seotips #onlinestore #technicalseo #blackfriday #woocommerce #ecommercetips #shopifystore #inventorymanagement #smallbusiness | R12: #ecommerceseo #shopifyseo #outofstock #seotips #onlinestore #technicalseo #blackfriday #woocommerce #ecommercetips #shopifystore #inventorymanagement #smallbusiness | S12: [0-3s] VO: We don't delete sold-out products. | ON-SCREEN: WE DON'T DELETE SOLD-OUT PRODUCTS. | VISUAL: Product card stamped SOLD OUT, a cursor hovers over Delete [3-5s] VO: We keep the page working for buyers. | ON-SCREEN: WE KEEP THE PAGE WORKING. | VISUAL: Cursor moves away, page stays [5-7s] VO: Most stores do this. | ON-SCREEN: MOST STORES: | VISUAL: Three quick cuts [7-8s] VO: Hide it. | ON-SCREEN: HIDE IT. | VISUAL: Eye icon slashed [8-9s] VO: Delete it. | ON-SCREEN: DELETE IT. | VISUAL: Bin icon [9-10s] VO: Forget it. | ON-SCREEN: FORGET IT. | VISUAL: 404 page [10-13s] VO: But first, ask three things. | ON-SCREEN: BUT FIRST, 3 QUESTIONS | VISUAL: Three numbered cards [13-16s] VO: Is it coming back? | ON-SCREEN: 1. COMING BACK? → KEEP IT LIVE | VISUAL: "Notify me" button [16-19s] VO: Is there a replacement? | ON-SCREEN: 2. REPLACEMENT? → 301 IT | VISUAL: Arrow to a new product [19-22s] VO: Does it have links? | ON-SCREEN: 3. HAS LINKS? → DON'T 404 IT | VISUAL: Chain links connecting to the page [22-25s] VO: Without those answers, a sold-out product becomes a dead page. | ON-SCREEN: SOLD OUT → DEAD PAGE | VISUAL: Page greys out [25-27s] VO: Sold out is only a stock problem. | ON-SCREEN: SOLD OUT IS A STOCK PROBLEM. | VISUAL: Box icon [27-30s] VO: Don't make it an SEO problem. | ON-SCREEN: DON'T MAKE IT AN SEO PROBLEM. | VISUAL: End card "Comment RESTOCK" + @Mehrooz · Permanent SEO | T12: Same video as Instagram Reel (upload natively, 9:16, add captions). See Instagram prompt → | U12: Produce a 1080x1920 vertical reel, 25–35 s. Visual style: soft white studio background with subtle grid and soft corner shadows, mostly monochrome (black, grey, white) with ONE accent colour blue #1566D7; cinematic 3D objects (rocket, credit card, balance scale, puzzle pieces, magnifying glass, Google/Shopify-style app icons) that move in with motion blur; kinetic typography: bold geometric sans, one or two words per beat, key word in large grey/blue. Permanent SEO logo small at top-centre throughout. Voiceover: calm, deep, confident male narrator; measured pace (~130 words/min); a short pause between every line; no hype, no music drops over the voice; subtle minimal ambient bed + soft whoosh on text changes. BEATS: [0-3s] VO: We don't delete sold-out products. | ON-SCREEN: WE DON'T DELETE SOLD-OUT PRODUCTS. | VISUAL: Product card stamped SOLD OUT, a cursor hovers over Delete [3-5s] VO: We keep the page working for buyers. | ON-SCREEN: WE KEEP THE PAGE WORKING. | VISUAL: Cursor moves away, page stays [5-7s] VO: Most stores do this. | ON-SCREEN: MOST STORES: | VISUAL: Three quick cuts [7-8s] VO: Hide it. | ON-SCREEN: HIDE IT. | VISUAL: Eye icon slashed [8-9s] VO: Delete it. | ON-SCREEN: DELETE IT. | VISUAL: Bin icon [9-10s] VO: Forget it. | ON-SCREEN: FORGET IT. | VISUAL: 404 page [10-13s] VO: But first, ask three things. | ON-SCREEN: BUT FIRST, 3 QUESTIONS | VISUAL: Three numbered cards [13-16s] VO: Is it coming back? | ON-SCREEN: 1. COMING BACK? → KEEP IT LIVE | VISUAL: "Notify me" button [16-19s] VO: Is there a replacement? | ON-SCREEN: 2. REPLACEMENT? → 301 IT | VISUAL: Arrow to a new product [19-22s] VO: Does it have links? | ON-SCREEN: 3. HAS LINKS? → DON'T 404 IT | VISUAL: Chain links connecting to the page [22-25s] VO: Without those answers, a sold-out product becomes a dead page. | ON-SCREEN: SOLD OUT → DEAD PAGE | VISUAL: Page greys out [25-27s] VO: Sold out is only a stock problem. | ON-SCREEN: SOLD OUT IS A STOCK PROBLEM. | VISUAL: Box icon [27-30s] VO: Don't make it an SEO problem. | ON-SCREEN: DON'T MAKE IT AN SEO PROBLEM. | VISUAL: End card "Comment RESTOCK" + @Mehrooz · Permanent SEO Final 3 s: dark/navy end card with Permanent SEO logo, 'SEO for E-commerce Brands' and 'Comment "RESTOCK"'. Burned-in captions. All text spelled exactly as written, sharp and legible on mobile; no extra words, no watermarks. | V12: RESTOCK | W12: Out-of-Stock Decision Tree (keep live vs 301 vs 404, one-page PDF) | X12: Product sold out? Don't delete the page. Coming back → keep it live + restock alerts Replacement exists → 301 No links, no replacement → let it 404 Sold out is a stock problem. Don't make it an SEO problem. #EcommerceSEO | Y12: Repost the Instagram caption + same visual as Facebook Reel | Z12: YouTube Shorts · Facebook Reels · X video | AA12: Out of Stock Products SEO: Don't Delete Sold-Out Pages | AB12: Out of stock products SEO in 30 seconds: when to keep a sold-out product page live, when to 301 redirect it, and when a 404 is fine. #Shorts | AC12: out of stock products SEO, sold out product page, shopify SEO, ecommerce SEO, 301 redirect, 404 errors, discontinued products, black friday SEO, technical SEO, Permanent SEO | AG12: 12:00 / 19:00 | AH12: Planned
A13: 9 | B13: 46338 | C13: Thu | D13: 2 | E13: Nov 2026 | F13: E-commerce SEO Foundations + Black Friday / Cyber Monday SEO | G13: Explainer | H13: LONG_VIDEO | I13: LinkedIn Long Video (16:9) | J13: Instagram Reel (30–45 s vertical cut) | K13: Internal linking for holiday collections before Black Friday | L13: Your Black Friday collection is live. Can Google even find it? | M13: internal linking for ecommerce | N13: holiday collection SEO, Shopify internal links, gift guide internal linking, black friday collection SEO | O13: A new holiday collection with no internal links is a page Google may barely notice. You built "Christmas gifts for him". It's live. It's in the sitemap. But nothing on your site points to it. So Google treats it as low priority. Internal links tell Google what matters on your store. Here's the setup we use for holiday collections: → Homepage: one clear link to the main seasonal hub (/black-friday or /gifts) → Main menu: a seasonal item from now until early January → Seasonal hub: links down to each gift or deal collection → Each collection: links back up to the hub and across to 2–3 related collections → Top 10 products: a short "part of our Christmas gift guide" link → Blog gift guides: link to the collection, not just single products Use descriptive anchor text. "Gifts for runners" beats "click here". The video shows how the structure looks. Comment "HUBLINKS" and I'll send you the Holiday Collection Internal Linking Map. #InternalLinking #EcommerceSEO #ShopifySEO #HolidaySEO | P13: #InternalLinking #EcommerceSEO #ShopifySEO #HolidaySEO | Q13: Your holiday collection is live. Does anything link to it? → Homepage link to the seasonal hub → Seasonal item in the main menu → Hub links to every gift collection → Collections link back and across → Top products link to the gift guide Clear anchor text. "Gifts for runners", not "click here". Save this before launch week. Comment "HUBLINKS" for the Holiday Collection Internal Linking Map. #internallinking #ecommerceseo #shopifyseo #seotips #christmasgifts #blackfriday #onlinestore #woocommerce #giftguide #ecommercetips #shopifystore #holidaymarketing | R13: #internallinking #ecommerceseo #shopifyseo #seotips #christmasgifts #blackfriday #onlinestore #woocommerce #giftguide #ecommercetips #shopifystore #holidaymarketing | S13: Scene 1 [0-10s] VO: "Right. Christmas gift collection, live. Black Friday collection, live. Now we just wait for Google." Long pause. "...Any day now." | VISUAL: Store owner animation, clock spinning, empty traffic graph Scene 2 [10-20s] VO: "Let's be honest. Your new collection isn't the problem. The problem is nothing on your store points to it." | VISUAL: Site map nodes, one isolated node blinking Scene 3 [20-32s] VO: "Google follows links to decide what matters. A page with no internal links looks like a page you don't care about. Meanwhile your competitor's gift guide sits in their menu, their homepage and every product page." | VISUAL: Competitor node lit up with many connecting lines Scene 4 [32-40s] VO: "Here's how Permanent SEO links holiday collections." | VISUAL: Logo, hub-and-spoke diagram building Scene 5 [40-52s] VO: "Step one. One seasonal hub on a permanent URL. Link it from the homepage and the main menu." | VISUAL: Homepage + menu arrows into hub Scene 6 [52-64s] VO: "Step two. The hub links down to every gift and deal collection. Each collection links back up, and across to two or three related ones." | VISUAL: Spokes and cross-links appear Scene 7 [64-76s] VO: "Step three. Your best sellers link to the collections they belong to. Your blog gift guides link to collections, not just single products." | VISUAL: Product page with a small text link highlighted Scene 8 [76-86s] VO: "Step four. Use anchor text people would search. Gifts for runners. Not click here." | VISUAL: Two anchor examples, one crossed out Scene 9 [86-94s] VO: "Here's what that did for one store: [CLIENT RESULT: +X% clicks to holiday collections]." | VISUAL: Placeholder results card Scene 10 [94-108s] VO: "Comment HUBLINKS for the linking map. Or book a free e-commerce SEO audit with Permanent SEO." | VISUAL: End card, keyword, Mehrooz + Permanent SEO | T13: Produce a 1920x1080 motion-graphics explainer, 60–120 s. Visual style: bright white/very light blue #F4F7FD canvas, floating UI mockups (Google results, Search Console charts, product pages, ChatGPT answers), kinetic typography where key words turn blue #1566D7, smooth parallax and soft shadows, occasional full-bleed blue #1566D7 scene with one giant word. Voiceover: calm, deep, confident male narrator; measured pace (~130 words/min); a short pause between every line; no hype, no music drops over the voice; subtle minimal ambient bed + soft whoosh on text changes. SCRIPT & SCENES: Scene 1 [0-10s] VO: "Right. Christmas gift collection, live. Black Friday collection, live. Now we just wait for Google." Long pause. "...Any day now." | VISUAL: Store owner animation, clock spinning, empty traffic graph Scene 2 [10-20s] VO: "Let's be honest. Your new collection isn't the problem. The problem is nothing on your store points to it." | VISUAL: Site map nodes, one isolated node blinking Scene 3 [20-32s] VO: "Google follows links to decide what matters. A page with no internal links looks like a page you don't care about. Meanwhile your competitor's gift guide sits in their menu, their homepage and every product page." | VISUAL: Competitor node lit up with many connecting lines Scene 4 [32-40s] VO: "Here's how Permanent SEO links holiday collections." | VISUAL: Logo, hub-and-spoke diagram building Scene 5 [40-52s] VO: "Step one. One seasonal hub on a permanent URL. Link it from the homepage and the main menu." | VISUAL: Homepage + menu arrows into hub Scene 6 [52-64s] VO: "Step two. The hub links down to every gift and deal collection. Each collection links back up, and across to two or three related ones." | VISUAL: Spokes and cross-links appear Scene 7 [64-76s] VO: "Step three. Your best sellers link to the collections they belong to. Your blog gift guides link to collections, not just single products." | VISUAL: Product page with a small text link highlighted Scene 8 [76-86s] VO: "Step four. Use anchor text people would search. Gifts for runners. Not click here." | VISUAL: Two anchor examples, one crossed out Scene 9 [86-94s] VO: "Here's what that did for one store: [CLIENT RESULT: +X% clicks to holiday collections]." | VISUAL: Placeholder results card Scene 10 [94-108s] VO: "Comment HUBLINKS for the linking map. Or book a free e-commerce SEO audit with Permanent SEO." | VISUAL: End card, keyword, Mehrooz + Permanent SEO End card: Permanent SEO logo + 'Comment "HUBLINKS"' + 'Muhammad Mehrooz Shafique · Co-Founder, Permanent SEO'. Burn in captions. All text spelled exactly as written, sharp and legible on mobile; no extra words, no watermarks. | U13: Produce a 1080x1920 vertical reel, 25–35 s. Visual style: soft white studio background with subtle grid and soft corner shadows, mostly monochrome (black, grey, white) with ONE accent colour blue #1566D7; cinematic 3D objects (rocket, credit card, balance scale, puzzle pieces, magnifying glass, Google/Shopify-style app icons) that move in with motion blur; kinetic typography: bold geometric sans, one or two words per beat, key word in large grey/blue. Permanent SEO logo small at top-centre throughout. Voiceover: calm, deep, confident male narrator; measured pace (~130 words/min); a short pause between every line; no hype, no music drops over the voice; subtle minimal ambient bed + soft whoosh on text changes. BEATS: Vertical 30–45 s cut of the long video: keep the opener, the problem line, the 3–4 steps as one-word beats and the CTA. Source script: Scene 1 [0-10s] VO: "Right. Christmas gift collection, live. Black Friday collection, live. Now we just wait for Google." Long pause. "...Any day now." | VISUAL: Store owner animation, clock spinning, empty traffic graph Scene 2 [10-20s] VO: "Let's be honest. Your new collection isn't the problem. The problem is nothing on your store points to it." | VISUAL: Site map nodes, one isolated node blinking Scene 3 [20-32s] VO: "Google follows links to decide what matters. A page with no internal links looks like a page you don't care about. Meanwhile your competitor's gift guide sits in their menu, their homepage and every product page." | VISUAL: Competitor node lit up with many connecting lines Scene 4 [32-40s] VO: "Here's how Permanent SEO links holiday collections." | VISUAL: Logo, hub-and-spoke diagram building Scene 5 [40-52s] VO: "Step one. One seasonal hub on a permanent URL. Link it from the homepage and the main menu." | VISUAL: Homepage + menu arrows into hub Scene 6 [52-64s] VO: "Step two. The hub links down to every gift and deal collection. Each collection links back up, and across to two or three related ones." | VISUAL: Spokes and cross-links appear Scene 7 [64-76s] VO: "Step three. Your best sellers link to the collections they belong to. Your blog gift guides link to collections, not just single products." | VISUAL: Product page with a small text link highlighted Scene 8 [76-86s] VO: "Step four. Use anchor text people would search. Gifts for runners. Not click here." | VISUAL: Two anchor examples, one crossed out Scene 9 [86-94s] VO: "Here's what that did for one store: [CLIENT RESULT: +X% clicks to holiday collections]." | VISUAL: Placeholder results card Scene 10 [94-108s] VO: "Comment HUBLINKS for the linking map. Or book a free e-commerce SEO audit with Permanent SEO." | VISUAL: End card, keyword, Mehrooz + Permanent SEO Final 3 s: dark/navy end card with Permanent SEO logo, 'SEO for E-commerce Brands' and 'Comment "HUBLINKS"'. Burned-in captions. All text spelled exactly as written, sharp and legible on mobile; no extra words, no watermarks. | V13: HUBLINKS | W13: Holiday Collection Internal Linking Map (hub-and-spoke template, Google Sheet + diagram) | X13: New holiday collection with zero internal links = low priority to Google. Fix: → Homepage + menu link to a seasonal hub → Hub links to every collection → Collections link back and across → Best sellers link to their collection #EcommerceSEO | Y13: Repost the Instagram caption + same visual (upload 16:9 natively) | Z13: YouTube long video · Facebook native video · X clip (first 45 s) | AA13: Internal Linking for Ecommerce: Get Holiday Collections Found | AB13: Internal linking for ecommerce explained with a simple hub-and-spoke setup for Black Friday and Christmas collections. Mehrooz Shafique from Permanent SEO shows the four steps that help Google find and prioritise your seasonal pages. | AC13: internal linking for ecommerce, holiday collection SEO, shopify internal links, black friday SEO, christmas gift guide SEO, ecommerce SEO, anchor text, site structure, woocommerce SEO, Permanent SEO | AG13: 08:30 / 18:30 | AH13: Planned
A14: 10 | B14: 46339 | C14: Fri | D14: 2 | E14: Nov 2026 | F14: E-commerce SEO Foundations + Black Friday / Cyber Monday SEO | G14: Proof & Freebie | H14: POST | I14: LinkedIn Post (detailed image) | J14: Instagram Post (single image) | K14: Case study: reviving a seasonal page instead of rebuilding it | L14: We didn't build a new Black Friday page. We fixed it. | M14: seasonal SEO case study | N14: black friday page case study, ecommerce SEO results, seasonal landing page results, old URL SEO | O14: [Client: UK homeware store] came to us in [MONTH] with a familiar setup. Five years of Black Friday sales. Five different URLs. Each one deleted or left as a 404 after the sale. Here's what we did: 1. Found every old seasonal URL in Search Console and their backlink profile 2. Chose one permanent URL: /black-friday 3. 301 redirected all the old yearly URLs to it 4. Rewrote the page: what's on sale, delivery cut-off dates, FAQs, links to each deal collection 5. Linked it from the homepage and main menu from early [MONTH] 6. After the sale, switched it to a "next sale" page with an email sign-up Results: → [CLIENT RESULT: page ranking position for "brand + black friday" before vs after] → [CLIENT RESULT: +X% organic clicks to the page vs last year] → [CLIENT RESULT: X email sign-ups from the off-season version] No new content budget. Just old pages put back to work. Comment "REVIVE" and I'll send you the Seasonal Page Revival SOP we used. #CaseStudy #EcommerceSEO #BlackFriday #ShopifySEO | P14: #CaseStudy #EcommerceSEO #BlackFriday #ShopifySEO | Q14: 5 years. 5 Black Friday URLs. All deleted. What we did: → Found every old URL → 301'd them to one permanent page → Rewrote it with deals, cut-offs, FAQs → Linked it from the homepage → Turned it into an email page after the sale Result: [CLIENT RESULT: +X% organic clicks] No new content budget. Just old pages put back to work. Comment "REVIVE" for the Seasonal Page Revival SOP. #seocasestudy #ecommerceseo #blackfriday #shopifyseo #seotips #onlinestore #seoresults #bfcm #woocommerce #ecommercetips #shopifystore #redirects | R14: #seocasestudy #ecommerceseo #blackfriday #shopifyseo #seotips #onlinestore #seoresults #bfcm #woocommerce #ecommercetips #shopifystore #redirects | S14: Single image, case study card, 1080x1350. Top label: CASE STUDY. Headline: WE FIXED THE OLD BLACK FRIDAY PAGE. Sub-headline: [Client: UK homeware store] · Shopify. Left block "BEFORE": 5 yearly URLs listed as struck-through browser bars (/black-friday-2021 ... /black-friday-2025), label "All 404 or deleted". Right block "AFTER": one green browser bar "/black-friday", label "One permanent URL". Middle: 6 numbered steps in small text: 1 Find old URLs · 2 Pick one URL · 3 301 redirects · 4 Rewrite page · 5 Homepage + menu links · 6 Off-season email version. Results row of three stat tiles (placeholders): [+X% organic clicks] · [Position X → Y for "brand black friday"] · [X email sign-ups]. Footer: Mehrooz Shafique · Permanent SEO | Banner: Comment "REVIVE" for the SOP | T14: Create a 1080x1350 LinkedIn infographic. Clean premium editorial style: off-white #F4F7FD background, primary blue #1566D7 accents, navy #191A46 text, headlines in Bebas Neue (bold condensed, all caps), body in Inter; generous margins, faint grid lines, crisp vector icons, no stock-photo clutter. HEADLINE: "We didn't build a new Black Friday page. We fixed it." SUBHEAD: "Case study: reviving a seasonal page instead of rebuilding it" MAIN VISUAL: the layout described below containing exactly: Single image, case study card, 1080x1350. Top label: CASE STUDY. Headline: WE FIXED THE OLD BLACK FRIDAY PAGE. Sub-headline: [Client: UK homeware store] · Shopify. Left block "BEFORE": 5 yearly URLs listed as struck-through browser bars (/black-friday-2021 ... /black-friday-2025), label "All 404 or deleted". Right block "AFTER": one green browser bar "/black-friday", label "One permanent URL". Middle: 6 numbered steps in small text: 1 Find old URLs · 2 Pick one URL · 3 301 redirects · 4 Rewrite page · 5 Homepage + menu links · 6 Off-season email version. Results row of three stat tiles (placeholders): [+X% organic clicks] · [Position X → Y for "brand black friday"] · [X email sign-ups]. Footer: Mehrooz Shafique · Permanent SEO | Banner: Comment "REVIVE" for the SOP CTA BANNER (bottom, navy rounded box, white text, keyword in blue): Comment "REVIVE" for Seasonal Page Revival SOP (step-by-step Google Doc) Footer on every frame: small circular headshot avatar + name tag 'Muhammad Mehrooz Shafique · Co-Founder, Permanent SEO' bottom-left; Permanent SEO 'P' logo (rising bar-chart + arrow mark) bottom-right. All text spelled exactly as written, sharp and legible on mobile; no extra words, no watermarks. | U14: Create a 1080x1350 Instagram post. Bold creator style: deep gradient background #345DF5 (top) to #191A46 (bottom), huge white Bebas Neue / Anton condensed headline, key words highlighted in #1566D7 highlight boxes or light-blue text, high contrast. HEADLINE (top, 2–3 lines, giant): "We didn't build a new Black Friday page. We fixed it." BODY (numbered points / simple visual): the 3–5 key points from this brief, shortened to max 8 words each: Single image, case study card, 1080x1350. Top label: CASE STUDY. Headline: WE FIXED THE OLD BLACK FRIDAY PAGE. Sub-headline: [Client: UK homeware store] · Shopify. Left block "BEFORE": 5 yearly URLs listed as struck-through browser bars (/black-friday-2021 ... /black-friday-2025), label "All 404 or deleted". Right block "AFTER": one green browser bar "/black-friday", label "One permanent URL". Middle: 6 numbered steps in small text: 1 Find old URLs · 2 Pick one URL · 3 301 redirects · 4 Rewrite page · 5 Homepage + menu links · 6 Off-season email version. Results row of three stat tiles (placeholders): [+X% organic clicks] · [Position X → Y for "brand black friday"] · [X email sign-ups]. Footer: Mehrooz Shafique · Permanent SEO | Banner: Comment "REVIVE" for the SOP BOTTOM BAR: Comment "REVIVE" for Seasonal Page Revival SOP (step-by-step Google Doc) Footer on every frame: small circular headshot avatar + name tag 'Muhammad Mehrooz Shafique · Co-Founder, Permanent SEO' bottom-left; Permanent SEO 'P' logo (rising bar-chart + arrow mark) bottom-right (white versions). All text spelled exactly as written, sharp and legible on mobile; no extra words, no watermarks. | V14: REVIVE | W14: Seasonal Page Revival SOP (step-by-step Google Doc) | X14: Case study: a store had 5 Black Friday URLs from 5 years. All 404. We 301'd them to one permanent /black-friday page, rewrote it and linked it from the homepage. Result: [CLIENT RESULT: +X% organic clicks]. #EcommerceSEO | Y14: Repost the Instagram caption + same visual | Z14: X post + image · Facebook image post | AG14: 09:00 / 12:30 | AH14: Planned
A15: 11 | B15: 46342 | C15: Mon | D15: 3 | E15: Nov 2026 | F15: E-commerce SEO Foundations + Black Friday / Cyber Monday SEO | G15: Educate | H15: SLIDE | I15: LinkedIn Slide Post (PDF carousel) | J15: Instagram Slide Post (carousel) | K15: Google Merchant Center free listings: setup in 7 steps | L15: Your products can show on Google Shopping for free. | M15: google merchant center free listings | N15: free product listings Google, Google Shopping free listings, Merchant Center Shopify, product feed SEO | O15: Google shows products in the Shopping tab and other surfaces without you paying for ads. It's called free listings, and it runs through Google Merchant Center. A lot of stores only use Merchant Center for paid Shopping ads. Or they never set it up at all. Here's the 7-step setup: 1. Create or open your Merchant Center account 2. Verify and claim your website 3. Add shipping and returns settings 4. Connect your product feed (Shopify and WooCommerce have official integrations) 5. Make sure free listings are switched on for your products 6. Fix disapprovals: missing GTINs, price mismatches, image issues 7. Add product structured data on your site so prices and stock match the feed Before Black Friday, check one more thing: sale prices. If your feed price doesn't match your page price, products can get disapproved right when you need them. The carousel goes step by step. Comment "FREELISTINGS" and I'll send you the Merchant Center Free Listings Setup Checklist. #GoogleMerchantCenter #EcommerceSEO #GoogleShopping #ShopifySEO | P15: #GoogleMerchantCenter #EcommerceSEO #GoogleShopping #ShopifySEO | Q15: Free product listings on Google. Most stores skip it. 1. Open Merchant Center 2. Verify your website 3. Add shipping + returns 4. Connect your product feed 5. Turn on free listings 6. Fix disapprovals 7. Match structured data to the feed Check sale prices match before Black Friday. A mismatch can get products disapproved. Save this. Comment "FREELISTINGS" for the Merchant Center Setup Checklist. #googlemerchantcenter #googleshopping #ecommerceseo #shopifyseo #seotips #onlinestore #productfeed #woocommerce #ecommercetips #shopifystore #blackfriday #smallbusiness | R15: #googlemerchantcenter #googleshopping #ecommerceseo #shopifyseo #seotips #onlinestore #productfeed #woocommerce #ecommercetips #shopifystore #blackfriday #smallbusiness | S15: Slide 1: Your products can show on Google Shopping for free. | Google Merchant Center free listings in 7 steps. Slide 2: What free listings are | Unpaid product listings across Google surfaces like the Shopping tab. Managed in Merchant Center. Slide 3: Step 1: Open Merchant Center | Create an account or log into the one your ads team set up. Slide 4: Step 2: Verify your website | Verify and claim your domain so Google trusts your feed. Slide 5: Step 3: Shipping + returns | Add delivery costs, times and your return policy. Missing info causes issues. Slide 6: Step 4: Connect your feed | Use the official Shopify or WooCommerce integration, or a scheduled feed file. Slide 7: Step 5: Turn on free listings | Check your products are opted in to free listings, not only Shopping ads. Slide 8: Step 6: Fix disapprovals | Common ones: missing GTIN, price mismatch, image with text overlay, unclear availability. Slide 9: Step 7: Match your structured data | Product schema on your site should show the same price and stock as the feed. Check sale prices before Black Friday. Slide 10: Comment "FREELISTINGS" | Get the Merchant Center Free Listings Setup Checklist. Follow Mehrooz for more store SEO. | T15: Design a 10-slide LinkedIn PDF carousel, 1080x1350 each. Clean premium editorial style: off-white #F4F7FD background, primary blue #1566D7 accents, navy #191A46 text, headlines in Bebas Neue (bold condensed, all caps), body in Inter; generous margins, faint grid lines, crisp vector icons, no stock-photo clutter. Cover slide like a premium guide cover: giant two-tone headline (key word in blue), small illustration/UI mockup, numbered contents list. Inner slides: big slide number in blue, Bebas Neue title, short Inter body, one diagram/mockup/checklist per slide. Last slide: navy CTA banner with download icon. SLIDE CONTENT: Slide 1: Your products can show on Google Shopping for free. | Google Merchant Center free listings in 7 steps. Slide 2: What free listings are | Unpaid product listings across Google surfaces like the Shopping tab. Managed in Merchant Center. Slide 3: Step 1: Open Merchant Center | Create an account or log into the one your ads team set up. Slide 4: Step 2: Verify your website | Verify and claim your domain so Google trusts your feed. Slide 5: Step 3: Shipping + returns | Add delivery costs, times and your return policy. Missing info causes issues. Slide 6: Step 4: Connect your feed | Use the official Shopify or WooCommerce integration, or a scheduled feed file. Slide 7: Step 5: Turn on free listings | Check your products are opted in to free listings, not only Shopping ads. Slide 8: Step 6: Fix disapprovals | Common ones: missing GTIN, price mismatch, image with text overlay, unclear availability. Slide 9: Step 7: Match your structured data | Product schema on your site should show the same price and stock as the feed. Check sale prices before Black Friday. Slide 10: Comment "FREELISTINGS" | Get the Merchant Center Free Listings Setup Checklist. Follow Mehrooz for more store SEO. Footer on every frame: small circular headshot avatar + name tag 'Muhammad Mehrooz Shafique · Co-Founder, Permanent SEO' bottom-left; Permanent SEO 'P' logo (rising bar-chart + arrow mark) bottom-right. All text spelled exactly as written, sharp and legible on mobile; no extra words, no watermarks. | U15: Design a 10-slide Instagram carousel, 1080x1350 each. Bold creator style: deep gradient background #345DF5 (top) to #191A46 (bottom), huge white Bebas Neue / Anton condensed headline, key words highlighted in #1566D7 highlight boxes or light-blue text, high contrast. Slide 1 = scroll-stopping cover with giant condensed headline and a 'swipe →' cue; inner slides alternate navy and white backgrounds, big blue slide number, max 25 words, one icon or mini-diagram each; last slide = CTA with comment keyword in a blue pill. SLIDE CONTENT: Slide 1: Your products can show on Google Shopping for free. | Google Merchant Center free listings in 7 steps. Slide 2: What free listings are | Unpaid product listings across Google surfaces like the Shopping tab. Managed in Merchant Center. Slide 3: Step 1: Open Merchant Center | Create an account or log into the one your ads team set up. Slide 4: Step 2: Verify your website | Verify and claim your domain so Google trusts your feed. Slide 5: Step 3: Shipping + returns | Add delivery costs, times and your return policy. Missing info causes issues. Slide 6: Step 4: Connect your feed | Use the official Shopify or WooCommerce integration, or a scheduled feed file. Slide 7: Step 5: Turn on free listings | Check your products are opted in to free listings, not only Shopping ads. Slide 8: Step 6: Fix disapprovals | Common ones: missing GTIN, price mismatch, image with text overlay, unclear availability. Slide 9: Step 7: Match your structured data | Product schema on your site should show the same price and stock as the feed. Check sale prices before Black Friday. Slide 10: Comment "FREELISTINGS" | Get the Merchant Center Free Listings Setup Checklist. Follow Mehrooz for more store SEO. Footer on every frame: small circular headshot avatar + name tag 'Muhammad Mehrooz Shafique · Co-Founder, Permanent SEO' bottom-left; Permanent SEO 'P' logo (rising bar-chart + arrow mark) bottom-right. All text spelled exactly as written, sharp and legible on mobile; no extra words, no watermarks. | V15: FREELISTINGS | W15: Merchant Center Free Listings Setup Checklist (PDF with common disapproval fixes) | X15: Your products can show in Google Shopping without paying for ads. It's called free listings, via Google Merchant Center. 7-step setup --- 1. Open Merchant Center 2. Verify and claim your website 3. Add shipping and returns settings --- 4. Connect your feed. Shopify and WooCommerce have official integrations. 5. Check your products are opted in to free listings, not only Shopping ads. --- 6. Fix disapprovals. The usual suspects: missing GTINs, price mismatches, images with text overlays. --- 7. Add Product structured data on your site so price and stock match the feed. --- Before Black Friday: check your sale prices match between page and feed. A mismatch can get products disapproved during the week you need them most. #EcommerceSEO | Y15: Repost the Instagram caption + same visual | Z15: X thread · Facebook carousel · Reddit text post | AD15: r/ecommerce | AE15: Reminder: Google Merchant Center free listings are worth setting up before Black Friday | AF15: Lots of store owners think Google Shopping is paid only. You can also get products shown through free listings in Merchant Center, and plenty of small stores never turn them on. Basic setup: 1. Create a Merchant Center account and verify/claim your site. 2. Add shipping and returns info. Missing details cause problems. 3. Connect a product feed. Shopify and WooCommerce both have official integrations, or you can upload a scheduled file. 4. Check that products are opted in to free listings and not just ads. 5. Work through the disapprovals. Usual causes are missing GTINs, prices that don't match the site, and images with promotional text. 6. Make sure the product structured data on your pages shows the same price and availability as your feed. One thing to watch this month: sale prices. If you change prices for Black Friday on the site but the feed lags behind, you can get mismatch warnings right when traffic peaks. Has anyone here seen meaningful traffic from free listings alone, without running Shopping ads? | AG15: 08:30 / 12:30 | AH15: Planned
A16: 12 | B16: 46343 | C16: Tue | D16: 3 | E16: Nov 2026 | F16: E-commerce SEO Foundations + Black Friday / Cyber Monday SEO | G16: Data & Insight | H16: POST | I16: LinkedIn Post (detailed image) | J16: Instagram Post (single image) | K16: Core Web Vitals thresholds every store should hit before peak | L16: Three numbers decide if your store feels fast on Black Friday. | M16: core web vitals for ecommerce | N16: LCP INP CLS thresholds, Shopify site speed, ecommerce page speed, mobile site speed SEO | O16: Google measures page experience with three Core Web Vitals. Here are Google's own "good" thresholds: → LCP (Largest Contentful Paint): 2.5 seconds or less How long your main image or headline takes to show. → INP (Interaction to Next Paint): 200 milliseconds or less How fast the page reacts when someone taps "Add to cart" or a filter. → CLS (Cumulative Layout Shift): 0.1 or less How much the page jumps around while loading. Google assesses these at the 75th percentile of real visits, so your slow visitors count. For stores, the usual culprits: → Huge hero images and sliders (LCP) → Too many apps and third-party scripts (INP) → Pop-ups, review widgets and banners loading late (CLS) Check yours now: Search Console → Core Web Vitals → Mobile. Fix "Poor" URLs before traffic peaks, not during. Comment "PEAKSPEED" and I'll send you the Pre-Peak Core Web Vitals Checklist. #CoreWebVitals #PageSpeed #EcommerceSEO #ShopifySEO | P16: #CoreWebVitals #PageSpeed #EcommerceSEO #ShopifySEO | Q16: 3 numbers. Google's "good" thresholds: → LCP ≤ 2.5s (main content shows) → INP ≤ 200ms (page reacts to taps) → CLS ≤ 0.1 (page doesn't jump) Store culprits: big sliders, too many apps, late pop-ups. Check: Search Console → Core Web Vitals → Mobile. Fix "Poor" URLs first. Save this before Black Friday. Comment "PEAKSPEED" for the Pre-Peak Core Web Vitals Checklist. #corewebvitals #pagespeed #sitespeed #ecommerceseo #shopifyseo #technicalseo #seotips #onlinestore #woocommerce #blackfriday #ecommercetips #shopifystore | R16: #corewebvitals #pagespeed #sitespeed #ecommerceseo #shopifyseo #technicalseo #seotips #onlinestore #woocommerce #blackfriday #ecommercetips #shopifystore | S16: Single image, data chart, 1080x1350. Headline: 3 NUMBERS THAT DECIDE IF YOUR STORE FEELS FAST. Sub-headline: Google's Core Web Vitals "good" thresholds. Three horizontal gauge bars, each split into Good (green) / Needs improvement (amber) / Poor (red) using Google's published bands: LCP: Good ≤2.5s | Needs improvement 2.5–4.0s | Poor >4.0s | caption "Main image or headline appears" INP: Good ≤200ms | Needs improvement 200–500ms | Poor >500ms | caption "Page reacts to Add to cart / filters" CLS: Good ≤0.1 | Needs improvement 0.1–0.25 | Poor >0.25 | caption "Page doesn't jump while loading" Below: "Common store culprits" three-cell table: LCP → oversized hero images & sliders | INP → too many apps & scripts | CLS → late pop-ups, review widgets, banners. Small note: "Measured at the 75th percentile of real visits. Source: Google (web.dev)". Footer: "Check: Search Console → Core Web Vitals → Mobile" · Mehrooz Shafique · Permanent SEO | Banner: Comment "PEAKSPEED" for the checklist | T16: Create a 1080x1350 LinkedIn infographic. Clean premium editorial style: off-white #F4F7FD background, primary blue #1566D7 accents, navy #191A46 text, headlines in Bebas Neue (bold condensed, all caps), body in Inter; generous margins, faint grid lines, crisp vector icons, no stock-photo clutter. HEADLINE: "Three numbers decide if your store feels fast on Black Friday." SUBHEAD: "Core Web Vitals thresholds every store should hit before peak" MAIN VISUAL: the layout described below containing exactly: Single image, data chart, 1080x1350. Headline: 3 NUMBERS THAT DECIDE IF YOUR STORE FEELS FAST. Sub-headline: Google's Core Web Vitals "good" thresholds. Three horizontal gauge bars, each split into Good (green) / Needs improvement (amber) / Poor (red) using Google's published bands: LCP: Good ≤2.5s | Needs improvement 2.5–4.0s | Poor >4.0s | caption "Main image or headline appears" INP: Good ≤200ms | Needs improvement 200–500ms | Poor >500ms | caption "Page reacts to Add to cart / filters" CLS: Good ≤0.1 | Needs improvement 0.1–0.25 | Poor >0.25 | caption "Page doesn't jump while loading" Below: "Common store culprits" three-cell table: LCP → oversized hero images & sliders | INP → too many apps & scripts | CLS → late pop-ups, review widgets, banners. Small note: "Measured at the 75th percentile of real visits. Source: Google (web.dev)". Footer: "Check: Search Console → Core Web Vitals → Mobile" · Mehrooz Shafique · Permanent SEO | Banner: Comment "PEAKSPEED" for the checklist CTA BANNER (bottom, navy rounded box, white text, keyword in blue): Comment "PEAKSPEED" for Pre-Peak Core Web Vitals Checklist for Shopify & WooCommerce (PDF) Footer on every frame: small circular headshot avatar + name tag 'Muhammad Mehrooz Shafique · Co-Founder, Permanent SEO' bottom-left; Permanent SEO 'P' logo (rising bar-chart + arrow mark) bottom-right. All text spelled exactly as written, sharp and legible on mobile; no extra words, no watermarks. | U16: Create a 1080x1350 Instagram post. Bold creator style: deep gradient background #345DF5 (top) to #191A46 (bottom), huge white Bebas Neue / Anton condensed headline, key words highlighted in #1566D7 highlight boxes or light-blue text, high contrast. HEADLINE (top, 2–3 lines, giant): "Three numbers decide if your store feels fast on Black Friday." BODY (numbered points / simple visual): the 3–5 key points from this brief, shortened to max 8 words each: Single image, data chart, 1080x1350. Headline: 3 NUMBERS THAT DECIDE IF YOUR STORE FEELS FAST. Sub-headline: Google's Core Web Vitals "good" thresholds. Three horizontal gauge bars, each split into Good (green) / Needs improvement (amber) / Poor (red) using Google's published bands: LCP: Good ≤2.5s | Needs improvement 2.5–4.0s | Poor >4.0s | caption "Main image or headline appears" INP: Good ≤200ms | Needs improvement 200–500ms | Poor >500ms | caption "Page reacts to Add to cart / filters" CLS: Good ≤0.1 | Needs improvement 0.1–0.25 | Poor >0.25 | caption "Page doesn't jump while loading" Below: "Common store culprits" three-cell table: LCP → oversized hero images & sliders | INP → too many apps & scripts | CLS → late pop-ups, review widgets, banners. Small note: "Measured at the 75th percentile of real visits. Source: Google (web.dev)". Footer: "Check: Search Console → Core Web Vitals → Mobile" · Mehrooz Shafique · Permanent SEO | Banner: Comment "PEAKSPEED" for the checklist BOTTOM BAR: Comment "PEAKSPEED" for Pre-Peak Core Web Vitals Checklist for Shopify & WooCommerce (PDF) Footer on every frame: small circular headshot avatar + name tag 'Muhammad Mehrooz Shafique · Co-Founder, Permanent SEO' bottom-left; Permanent SEO 'P' logo (rising bar-chart + arrow mark) bottom-right (white versions). All text spelled exactly as written, sharp and legible on mobile; no extra words, no watermarks. | V16: PEAKSPEED | W16: Pre-Peak Core Web Vitals Checklist for Shopify & WooCommerce (PDF) | X16: Google's Core Web Vitals "good" thresholds: LCP ≤ 2.5s INP ≤ 200ms CLS ≤ 0.1 Store culprits: giant sliders, app scripts, late pop-ups. Check Search Console → Core Web Vitals → Mobile before Black Friday. #CoreWebVitals #SEO | Y16: Repost the Instagram caption + same visual | Z16: X post + image · Facebook image post | AG16: 08:30 / 18:30 | AH16: Planned
A17: 13 | B17: 46344 | C17: Wed | D17: 3 | E17: Nov 2026 | F17: E-commerce SEO Foundations + Black Friday / Cyber Monday SEO | G17: Myth-Busting | H17: REEL | I17: LinkedIn native vertical video | J17: Instagram Reel (9:16) | K17: Myth: category pages don't need written content | L17: We don't leave collection pages empty. We give them words. | M17: collection page SEO | N17: category page content, Shopify collection description, ecommerce category SEO, category page copy | O17: "It's a category page. People just want to see products." That's true for the shopper. It's not the full story for Google. A collection page with only a product grid gives Google very little to understand. Product names and prices. That's it. Every competitor selling the same products has the same grid. What makes your collection different: → A short intro (2–3 lines) above the grid saying what's in it and who it's for → Helpful copy below the grid: sizing, materials, how to choose → 3–5 FAQs people actually ask → Links to related collections Not a wall of keyword-stuffed text. Useful words that help someone choose. Products give the page stock. Words give it a reason to rank. Comment "CATCOPY" and I'll send you the Collection Page Copy Template. #EcommerceSEO #CategoryPages #ShopifySEO #SEOCopywriting | P17: #EcommerceSEO #CategoryPages #ShopifySEO #SEOCopywriting | Q17: Empty collection page = nothing for Google to read. → 2–3 line intro above the grid → Buying help below it → 3–5 real FAQs → Links to related collections Useful words. Not keyword stuffing. Products give it stock. Words give it a reason to rank. Share this with your copywriter or whoever edits your store. Comment "CATCOPY" for the Collection Page Copy Template. #ecommerceseo #shopifyseo #seocopywriting #collectionpage #seotips #onlinestore #woocommerce #ecommercetips #shopifystore #contentwriting #productcopy #smallbusiness | R17: #ecommerceseo #shopifyseo #seocopywriting #collectionpage #seotips #onlinestore #woocommerce #ecommercetips #shopifystore #contentwriting #productcopy #smallbusiness | S17: [0-3s] VO: We don't leave collection pages empty. | ON-SCREEN: WE DON'T LEAVE COLLECTION PAGES EMPTY. | VISUAL: Product grid with no text, wide empty header [3-5s] VO: We give them words. | ON-SCREEN: WE GIVE THEM WORDS. | VISUAL: Text lines type in above the grid [5-7s] VO: Most stores stop here. | ON-SCREEN: MOST STORES STOP AT: | VISUAL: Grid zooms out [7-8s] VO: Photos. | ON-SCREEN: PHOTOS. | VISUAL: Image tiles [8-9s] VO: Prices. | ON-SCREEN: PRICES. | VISUAL: Price tags [9-10s] VO: Filters. | ON-SCREEN: FILTERS. | VISUAL: Filter sidebar [10-13s] VO: But first, three things need to be on the page. | ON-SCREEN: BUT FIRST, 3 THINGS | VISUAL: Three slots appear [13-16s] VO: What is in this collection? | ON-SCREEN: 1. WHAT'S IN IT? | VISUAL: Intro line highlights [16-19s] VO: Who is it for? | ON-SCREEN: 2. WHO IS IT FOR? | VISUAL: Audience line highlights [19-22s] VO: How do I choose? | ON-SCREEN: 3. HOW DO I CHOOSE? | VISUAL: FAQ accordion opens [22-25s] VO: Without those answers, your page looks like every competitor's. | ON-SCREEN: = EVERY COMPETITOR'S PAGE | VISUAL: Five identical grids side by side [25-27s] VO: Products give it stock. | ON-SCREEN: PRODUCTS GIVE IT STOCK. | VISUAL: Grid [27-30s] VO: Words give it a reason to rank. | ON-SCREEN: WORDS GIVE IT A REASON TO RANK. | VISUAL: End card "Comment CATCOPY" + @Mehrooz · Permanent SEO | T17: Same video as Instagram Reel (upload natively, 9:16, add captions). See Instagram prompt → | U17: Produce a 1080x1920 vertical reel, 25–35 s. Visual style: soft white studio background with subtle grid and soft corner shadows, mostly monochrome (black, grey, white) with ONE accent colour blue #1566D7; cinematic 3D objects (rocket, credit card, balance scale, puzzle pieces, magnifying glass, Google/Shopify-style app icons) that move in with motion blur; kinetic typography: bold geometric sans, one or two words per beat, key word in large grey/blue. Permanent SEO logo small at top-centre throughout. Voiceover: calm, deep, confident male narrator; measured pace (~130 words/min); a short pause between every line; no hype, no music drops over the voice; subtle minimal ambient bed + soft whoosh on text changes. BEATS: [0-3s] VO: We don't leave collection pages empty. | ON-SCREEN: WE DON'T LEAVE COLLECTION PAGES EMPTY. | VISUAL: Product grid with no text, wide empty header [3-5s] VO: We give them words. | ON-SCREEN: WE GIVE THEM WORDS. | VISUAL: Text lines type in above the grid [5-7s] VO: Most stores stop here. | ON-SCREEN: MOST STORES STOP AT: | VISUAL: Grid zooms out [7-8s] VO: Photos. | ON-SCREEN: PHOTOS. | VISUAL: Image tiles [8-9s] VO: Prices. | ON-SCREEN: PRICES. | VISUAL: Price tags [9-10s] VO: Filters. | ON-SCREEN: FILTERS. | VISUAL: Filter sidebar [10-13s] VO: But first, three things need to be on the page. | ON-SCREEN: BUT FIRST, 3 THINGS | VISUAL: Three slots appear [13-16s] VO: What is in this collection? | ON-SCREEN: 1. WHAT'S IN IT? | VISUAL: Intro line highlights [16-19s] VO: Who is it for? | ON-SCREEN: 2. WHO IS IT FOR? | VISUAL: Audience line highlights [19-22s] VO: How do I choose? | ON-SCREEN: 3. HOW DO I CHOOSE? | VISUAL: FAQ accordion opens [22-25s] VO: Without those answers, your page looks like every competitor's. | ON-SCREEN: = EVERY COMPETITOR'S PAGE | VISUAL: Five identical grids side by side [25-27s] VO: Products give it stock. | ON-SCREEN: PRODUCTS GIVE IT STOCK. | VISUAL: Grid [27-30s] VO: Words give it a reason to rank. | ON-SCREEN: WORDS GIVE IT A REASON TO RANK. | VISUAL: End card "Comment CATCOPY" + @Mehrooz · Permanent SEO Final 3 s: dark/navy end card with Permanent SEO logo, 'SEO for E-commerce Brands' and 'Comment "CATCOPY"'. Burned-in captions. All text spelled exactly as written, sharp and legible on mobile; no extra words, no watermarks. | V17: CATCOPY | W17: Collection Page Copy Template (intro, buying help and FAQ structure, Google Doc) | X17: A collection page with only a product grid looks like every competitor's. Add: → 2–3 line intro → Buying help below the grid → 3–5 real FAQs → Related collection links Products give it stock. Words give it a reason to rank. #EcommerceSEO | Y17: Repost the Instagram caption + same visual as Facebook Reel | Z17: YouTube Shorts · Facebook Reels · X video | AA17: Collection Page SEO: Why Category Pages Need Words | AB17: Collection page SEO in 30 seconds: why an empty product grid struggles to rank and the three questions every category page should answer. #Shorts | AC17: collection page SEO, category page SEO, shopify collection description, ecommerce SEO, category page content, shopify SEO, woocommerce SEO, SEO copywriting, online store SEO, Permanent SEO | AG17: 12:00 / 19:00 | AH17: Planned
A18: 14 | B18: 46345 | C18: Thu | D18: 3 | E18: Nov 2026 | F18: E-commerce SEO Foundations + Black Friday / Cyber Monday SEO | G18: Explainer | H18: LONG_VIDEO | I18: LinkedIn Long Video (16:9) | J18: Instagram Reel (30–45 s vertical cut) | K18: Site speed before peak traffic: the app bloat audit | L18: Every app you installed is still loading. Even the ones you forgot. | M18: shopify site speed optimization | N18: shopify app bloat, ecommerce page speed, speed up online store, third party scripts ecommerce | O18: Quick question: how many apps does your store run? Now, how many of them do you actually use? Most stores we audit have apps they tried once, uninstalled, and forgot. Some still leave code behind in the theme. Every script adds load time, mostly on mobile. And in Black Friday week, when traffic is highest, slow pages hurt most. The app bloat audit we run: 1. List every installed app and what it does 2. Remove anything unused or duplicated (two review apps, three pop-ups) 3. Check the theme for leftover code from removed apps 4. Test your top 5 pages on PageSpeed Insights, mobile 5. Compress and resize hero images and sliders 6. Delay non-essential scripts like chat widgets until after load Do this a week before peak, not on the day. Then don't install anything new until December. The video walks through it. Comment "APPBLOAT" and I'll send you the App Bloat Audit Sheet. #SiteSpeed #ShopifySEO #EcommerceSEO #CoreWebVitals | P18: #SiteSpeed #ShopifySEO #EcommerceSEO #CoreWebVitals | Q18: Every app you installed is still loading. Even the forgotten ones. 1. List every app 2. Remove unused + duplicates 3. Clean leftover theme code 4. Test top 5 pages on mobile 5. Compress hero images 6. Delay chat widgets Do it before peak. Not on the day. Then install nothing new until December. Save this. Comment "APPBLOAT" for the App Bloat Audit Sheet. #sitespeed #pagespeed #shopifyseo #shopifyapps #ecommerceseo #corewebvitals #technicalseo #seotips #onlinestore #shopifystore #blackfriday #ecommercetips | R18: #sitespeed #pagespeed #shopifyseo #shopifyapps #ecommerceseo #corewebvitals #technicalseo #seotips #onlinestore #shopifystore #blackfriday #ecommercetips | S18: Scene 1 [0-10s] VO: "Okay, a review app, a pop-up app, another pop-up app... wait, why do I have three pop-up apps?" | VISUAL: Animated store owner scrolling a long app list, list keeps growing Scene 2 [10-20s] VO: "Let's be honest. Your store isn't slow because of your products. It's slow because of everything loading around them." | VISUAL: Product page with dozens of script tags piling on top Scene 3 [20-32s] VO: "Every app adds scripts. Some leave code behind even after you remove them. On a phone, on Black Friday, that's the moment shoppers wait and leave." | VISUAL: Phone loading bar crawling, a shopper icon walking away Scene 4 [32-40s] VO: "Here's the app bloat audit we run at Permanent SEO before every peak season." | VISUAL: Logo, checklist appears Scene 5 [40-52s] VO: "Step one. List every app. Remove anything unused or duplicated. Two review apps is one too many." | VISUAL: App list, items swiping off Scene 6 [52-64s] VO: "Step two. Check your theme for leftover code from apps you already deleted." | VISUAL: Code editor, old snippet highlighted and removed Scene 7 [64-76s] VO: "Step three. Test your top five pages on PageSpeed Insights, on mobile. Aim for LCP under two and a half seconds and INP under two hundred milliseconds." | VISUAL: PageSpeed gauge, thresholds labelled Scene 8 [76-88s] VO: "Step four. Compress hero images. Delay chat widgets and anything that isn't needed to buy." | VISUAL: Image file size shrinking, chat bubble loading later Scene 9 [88-96s] VO: "One store we worked with: [CLIENT RESULT: mobile LCP from Xs to Ys]." | VISUAL: Placeholder before/after card Scene 10 [96-110s] VO: "Comment APPBLOAT for the audit sheet. Or book a free e-commerce SEO audit with Permanent SEO." | VISUAL: End card, keyword, Mehrooz + Permanent SEO | T18: Produce a 1920x1080 motion-graphics explainer, 60–120 s. Visual style: bright white/very light blue #F4F7FD canvas, floating UI mockups (Google results, Search Console charts, product pages, ChatGPT answers), kinetic typography where key words turn blue #1566D7, smooth parallax and soft shadows, occasional full-bleed blue #1566D7 scene with one giant word. Voiceover: calm, deep, confident male narrator; measured pace (~130 words/min); a short pause between every line; no hype, no music drops over the voice; subtle minimal ambient bed + soft whoosh on text changes. SCRIPT & SCENES: Scene 1 [0-10s] VO: "Okay, a review app, a pop-up app, another pop-up app... wait, why do I have three pop-up apps?" | VISUAL: Animated store owner scrolling a long app list, list keeps growing Scene 2 [10-20s] VO: "Let's be honest. Your store isn't slow because of your products. It's slow because of everything loading around them." | VISUAL: Product page with dozens of script tags piling on top Scene 3 [20-32s] VO: "Every app adds scripts. Some leave code behind even after you remove them. On a phone, on Black Friday, that's the moment shoppers wait and leave." | VISUAL: Phone loading bar crawling, a shopper icon walking away Scene 4 [32-40s] VO: "Here's the app bloat audit we run at Permanent SEO before every peak season." | VISUAL: Logo, checklist appears Scene 5 [40-52s] VO: "Step one. List every app. Remove anything unused or duplicated. Two review apps is one too many." | VISUAL: App list, items swiping off Scene 6 [52-64s] VO: "Step two. Check your theme for leftover code from apps you already deleted." | VISUAL: Code editor, old snippet highlighted and removed Scene 7 [64-76s] VO: "Step three. Test your top five pages on PageSpeed Insights, on mobile. Aim for LCP under two and a half seconds and INP under two hundred milliseconds." | VISUAL: PageSpeed gauge, thresholds labelled Scene 8 [76-88s] VO: "Step four. Compress hero images. Delay chat widgets and anything that isn't needed to buy." | VISUAL: Image file size shrinking, chat bubble loading later Scene 9 [88-96s] VO: "One store we worked with: [CLIENT RESULT: mobile LCP from Xs to Ys]." | VISUAL: Placeholder before/after card Scene 10 [96-110s] VO: "Comment APPBLOAT for the audit sheet. Or book a free e-commerce SEO audit with Permanent SEO." | VISUAL: End card, keyword, Mehrooz + Permanent SEO End card: Permanent SEO logo + 'Comment "APPBLOAT"' + 'Muhammad Mehrooz Shafique · Co-Founder, Permanent SEO'. Burn in captions. All text spelled exactly as written, sharp and legible on mobile; no extra words, no watermarks. | U18: Produce a 1080x1920 vertical reel, 25–35 s. Visual style: soft white studio background with subtle grid and soft corner shadows, mostly monochrome (black, grey, white) with ONE accent colour blue #1566D7; cinematic 3D objects (rocket, credit card, balance scale, puzzle pieces, magnifying glass, Google/Shopify-style app icons) that move in with motion blur; kinetic typography: bold geometric sans, one or two words per beat, key word in large grey/blue. Permanent SEO logo small at top-centre throughout. Voiceover: calm, deep, confident male narrator; measured pace (~130 words/min); a short pause between every line; no hype, no music drops over the voice; subtle minimal ambient bed + soft whoosh on text changes. BEATS: Vertical 30–45 s cut of the long video: keep the opener, the problem line, the 3–4 steps as one-word beats and the CTA. Source script: Scene 1 [0-10s] VO: "Okay, a review app, a pop-up app, another pop-up app... wait, why do I have three pop-up apps?" | VISUAL: Animated store owner scrolling a long app list, list keeps growing Scene 2 [10-20s] VO: "Let's be honest. Your store isn't slow because of your products. It's slow because of everything loading around them." | VISUAL: Product page with dozens of script tags piling on top Scene 3 [20-32s] VO: "Every app adds scripts. Some leave code behind even after you remove them. On a phone, on Black Friday, that's the moment shoppers wait and leave." | VISUAL: Phone loading bar crawling, a shopper icon walking away Scene 4 [32-40s] VO: "Here's the app bloat audit we run at Permanent SEO before every peak season." | VISUAL: Logo, checklist appears Scene 5 [40-52s] VO: "Step one. List every app. Remove anything unused or duplicated. Two review apps is one too many." | VISUAL: App list, items swiping off Scene 6 [52-64s] VO: "Step two. Check your theme for leftover code from apps you already deleted." | VISUAL: Code editor, old snippet highlighted and removed Scene 7 [64-76s] VO: "Step three. Test your top five pages on PageSpeed Insights, on mobile. Aim for LCP under two and a half seconds and INP under two hundred milliseconds." | VISUAL: PageSpeed gauge, thresholds labelled Scene 8 [76-88s] VO: "Step four. Compress hero images. Delay chat widgets and anything that isn't needed to buy." | VISUAL: Image file size shrinking, chat bubble loading later Scene 9 [88-96s] VO: "One store we worked with: [CLIENT RESULT: mobile LCP from Xs to Ys]." | VISUAL: Placeholder before/after card Scene 10 [96-110s] VO: "Comment APPBLOAT for the audit sheet. Or book a free e-commerce SEO audit with Permanent SEO." | VISUAL: End card, keyword, Mehrooz + Permanent SEO Final 3 s: dark/navy end card with Permanent SEO logo, 'SEO for E-commerce Brands' and 'Comment "APPBLOAT"'. Burned-in captions. All text spelled exactly as written, sharp and legible on mobile; no extra words, no watermarks. | V18: APPBLOAT | W18: App Bloat Audit Sheet (app inventory + speed test log, Google Sheet) | X18: Your store isn't slow because of your products. It's slow because of everything loading around them. Before Black Friday: → Remove unused apps → Clean leftover theme code → Test top 5 pages on mobile → Compress hero images #ShopifySEO | Y18: Repost the Instagram caption + same visual (upload 16:9 natively) | Z18: YouTube long video · Facebook native video · X clip (first 45 s) | AA18: Shopify Site Speed Optimization: The App Bloat Audit Before Peak | AB18: Shopify site speed optimization before Black Friday. Mehrooz Shafique from Permanent SEO shows how unused apps and leftover scripts slow your store, and the audit to fix it before peak traffic. | AC18: shopify site speed optimization, shopify app bloat, page speed, core web vitals, ecommerce SEO, shopify SEO, pagespeed insights, black friday prep, mobile site speed, Permanent SEO | AG18: 08:30 / 18:30 | AH18: Planned
A19: 15 | B19: 46346 | C19: Fri | D19: 3 | E19: Nov 2026 | F19: E-commerce SEO Foundations + Black Friday / Cyber Monday SEO | G19: Proof & Freebie | H19: POST | I19: LinkedIn Post (detailed image) | J19: Instagram Post (single image) | K19: Prompt share: 5 AI prompts for Black Friday title tags and metas | L19: 5 AI prompts I use to write Black Friday title tags. | M19: AI prompts for meta descriptions | N19: ChatGPT title tags, black friday meta description, ecommerce title tag examples, AI SEO prompts | O19: AI can write title tags. Most of what it writes is generic. "Shop Amazing Black Friday Deals Today!" tells Google and shoppers nothing. The fix is giving it the right inputs. These are 5 prompts I use for seasonal pages: 1. Title tag from real queries "Here are the top 10 Search Console queries for this page: [PASTE]. Write 5 title tags under 60 characters that include the main query and the offer." 2. Meta description with specifics "Write a meta description under 155 characters for [COLLECTION] mentioning [DISCOUNT], [DELIVERY CUT-OFF] and [RETURNS POLICY]." 3. Collection intro "Write a 2-sentence intro for [COLLECTION] for [AUDIENCE]. No hype words." 4. FAQ generator "List 5 questions buyers ask before buying [PRODUCT TYPE] in a sale." 5. Off-season rewrite "Rewrite this Black Friday page intro for January, keeping the URL's purpose." Always check facts before publishing. AI doesn't know your delivery dates. Comment "METAPROMPTS" and I'll send you the full Seasonal SEO Prompt Pack. #AIForSEO #EcommerceSEO #BlackFriday #ChatGPT | P19: #AIForSEO #EcommerceSEO #BlackFriday #ChatGPT | Q19: 5 AI prompts for Black Friday SEO: → Title tags from real Search Console queries → Meta descriptions with discount + delivery cut-off → 2-sentence collection intros → Pre-purchase FAQs → Off-season page rewrites Give AI real inputs, like your actual Search Console queries. Check every fact before publishing. AI doesn't know your delivery dates. Save this for your next update. Comment "METAPROMPTS" for the Seasonal SEO Prompt Pack. #aiprompts #chatgptprompts #ecommerceseo #blackfriday #shopifyseo #seotips #metadescription #titletags #onlinestore #ecommercetips #aiforbusiness #copywriting | R19: #aiprompts #chatgptprompts #ecommerceseo #blackfriday #shopifyseo #seotips #metadescription #titletags #onlinestore #ecommercetips #aiforbusiness #copywriting | S19: Single image "tool share", 1080x1350. Headline: 5 AI PROMPTS FOR BLACK FRIDAY TITLE TAGS. Sub-headline: Give it real inputs. Get useful output. Layout: five stacked "chat bubble" cards, each with a number, prompt name and the prompt text in monospace, placeholders highlighted in accent colour: 01 TITLE TAG FROM REAL QUERIES — "Here are the top 10 Search Console queries for this page: [PASTE]. Write 5 title tags under 60 characters..." 02 META WITH SPECIFICS — "...under 155 characters for [COLLECTION] mentioning [DISCOUNT], [DELIVERY CUT-OFF], [RETURNS]." 03 COLLECTION INTRO — "Write a 2-sentence intro for [COLLECTION] for [AUDIENCE]. No hype words." 04 FAQ GENERATOR — "List 5 questions buyers ask before buying [PRODUCT TYPE] in a sale." 05 OFF-SEASON REWRITE — "Rewrite this Black Friday intro for January..." Side callout: ❌ "Shop Amazing Black Friday Deals Today!" vs ✅ "Running Shoes Black Friday Sale: Up to [X]% Off | [Brand]". Footer warning strip: "Check facts. AI doesn't know your delivery dates." Banner: Comment "METAPROMPTS" for the full prompt pack. | T19: Create a 1080x1350 LinkedIn infographic. Clean premium editorial style: off-white #F4F7FD background, primary blue #1566D7 accents, navy #191A46 text, headlines in Bebas Neue (bold condensed, all caps), body in Inter; generous margins, faint grid lines, crisp vector icons, no stock-photo clutter. HEADLINE: "5 AI prompts I use to write Black Friday title tags." SUBHEAD: "Prompt share: 5 AI prompts for Black Friday title tags and metas" MAIN VISUAL: the layout described below containing exactly: Single image "tool share", 1080x1350. Headline: 5 AI PROMPTS FOR BLACK FRIDAY TITLE TAGS. Sub-headline: Give it real inputs. Get useful output. Layout: five stacked "chat bubble" cards, each with a number, prompt name and the prompt text in monospace, placeholders highlighted in accent colour: 01 TITLE TAG FROM REAL QUERIES — "Here are the top 10 Search Console queries for this page: [PASTE]. Write 5 title tags under 60 characters..." 02 META WITH SPECIFICS — "...under 155 characters for [COLLECTION] mentioning [DISCOUNT], [DELIVERY CUT-OFF], [RETURNS]." 03 COLLECTION INTRO — "Write a 2-sentence intro for [COLLECTION] for [AUDIENCE]. No hype words." 04 FAQ GENERATOR — "List 5 questions buyers ask before buying [PRODUCT TYPE] in a sale." 05 OFF-SEASON REWRITE — "Rewrite this Black Friday intro for January..." Side callout: ❌ "Shop Amazing Black Friday Deals Today!" vs ✅ "Running Shoes Black Friday Sale: Up to [X]% Off | [Brand]". Footer warning strip: "Check facts. AI doesn't know your delivery dates." Banner: Comment "METAPROMPTS" for the full prompt pack. CTA BANNER (bottom, navy rounded box, white text, keyword in blue): Comment "METAPROMPTS" for Seasonal SEO Prompt Pack (15 ChatGPT/Claude prompts for titles, metas, intros and FAQs) Footer on every frame: small circular headshot avatar + name tag 'Muhammad Mehrooz Shafique · Co-Founder, Permanent SEO' bottom-left; Permanent SEO 'P' logo (rising bar-chart + arrow mark) bottom-right. All text spelled exactly as written, sharp and legible on mobile; no extra words, no watermarks. | U19: Create a 1080x1350 Instagram post. Bold creator style: deep gradient background #345DF5 (top) to #191A46 (bottom), huge white Bebas Neue / Anton condensed headline, key words highlighted in #1566D7 highlight boxes or light-blue text, high contrast. HEADLINE (top, 2–3 lines, giant): "5 AI prompts I use to write Black Friday title tags." BODY (numbered points / simple visual): the 3–5 key points from this brief, shortened to max 8 words each: Single image "tool share", 1080x1350. Headline: 5 AI PROMPTS FOR BLACK FRIDAY TITLE TAGS. Sub-headline: Give it real inputs. Get useful output. Layout: five stacked "chat bubble" cards, each with a number, prompt name and the prompt text in monospace, placeholders highlighted in accent colour: 01 TITLE TAG FROM REAL QUERIES — "Here are the top 10 Search Console queries for this page: [PASTE]. Write 5 title tags under 60 characters..." 02 META WITH SPECIFICS — "...under 155 characters for [COLLECTION] mentioning [DISCOUNT], [DELIVERY CUT-OFF], [RETURNS]." 03 COLLECTION INTRO — "Write a 2-sentence intro for [COLLECTION] for [AUDIENCE]. No hype words." 04 FAQ GENERATOR — "List 5 questions buyers ask before buying [PRODUCT TYPE] in a sale." 05 OFF-SEASON REWRITE — "Rewrite this Black Friday intro for January..." Side callout: ❌ "Shop Amazing Black Friday Deals Today!" vs ✅ "Running Shoes Black Friday Sale: Up to [X]% Off | [Brand]". Footer warning strip: "Check facts. AI doesn't know your delivery dates." Banner: Comment "METAPROMPTS" for the full prompt pack. BOTTOM BAR: Comment "METAPROMPTS" for Seasonal SEO Prompt Pack (15 ChatGPT/Claude prompts for titles, metas, intros and FAQs) Footer on every frame: small circular headshot avatar + name tag 'Muhammad Mehrooz Shafique · Co-Founder, Permanent SEO' bottom-left; Permanent SEO 'P' logo (rising bar-chart + arrow mark) bottom-right (white versions). All text spelled exactly as written, sharp and legible on mobile; no extra words, no watermarks. | V19: METAPROMPTS | W19: Seasonal SEO Prompt Pack (15 ChatGPT/Claude prompts for titles, metas, intros and FAQs) | X19: AI writes generic title tags because we give it generic inputs. Better: paste your top 10 Search Console queries for the page and ask for 5 titles under 60 characters with the offer in them. Then check every fact. #AIForSEO #BlackFriday | Y19: Repost the Instagram caption + same visual | Z19: X post + image · Facebook image post | AG19: 09:00 / 12:30 | AH19: Planned
A20: 16 | B20: 46349 | C20: Mon | D20: 4 | E20: Nov 2026 | F20: E-commerce SEO Foundations + Black Friday / Cyber Monday SEO | G20: Educate | H20: SLIDE | I20: LinkedIn Slide Post (PDF carousel) | J20: Instagram Slide Post (carousel) | K20: Black Friday week: the final 7-day store SEO checklist | L20: Black Friday is Friday. Here's your SEO checklist for this week. | M20: black friday SEO checklist for ecommerce | N20: BFCM week SEO, last minute black friday SEO, black friday store prep, cyber monday SEO checklist | O20: Black Friday is this Friday, 27 November. Cyber Monday is 30 November. This is not the week for a redesign. It's the week to make sure nothing breaks. Here's the 7-day checklist, one job per day: Mon → Confirm your permanent /black-friday page is indexed (URL Inspection in Search Console) Tue → Homepage and menu link to the seasonal hub Wed → Sale prices match between site, structured data and Merchant Center feed Thu → Test top 5 sale pages on mobile speed Fri → Watch out-of-stock products. Keep pages live, link alternatives Sat → Check Search Console for crawl or indexing errors on sale URLs Sun → Prepare the Cyber Monday update on the same hub, not a new page And one rule: no new apps, no theme changes, no URL changes this week. Swipe through for what to check each day. Comment "LAUNCHWEEK" and I'll send you the Black Friday Week SEO Checklist. #BlackFriday #CyberMonday #EcommerceSEO #ShopifySEO | P20: #BlackFriday #CyberMonday #EcommerceSEO #ShopifySEO | Q20: Black Friday is Friday. Your 7-day SEO checklist: Mon → Seasonal page indexed? Tue → Homepage + menu links Wed → Prices match site + feed Thu → Mobile speed test Fri → Out-of-stock pages stay live Sat → Search Console errors Sun → Cyber Monday on the same page No new apps. No theme changes this week. Save this. Comment "LAUNCHWEEK" for the Black Friday Week SEO Checklist. #blackfriday #cybermonday #bfcm #blackfridayweek #ecommerceseo #shopifyseo #seotips #onlinestore #ecommercetips #shopifystore #woocommerce #smallbusiness #holidaysales | R20: #blackfriday #cybermonday #bfcm #blackfridayweek #ecommerceseo #shopifyseo #seotips #onlinestore #ecommercetips #shopifystore #woocommerce #smallbusiness #holidaysales | S20: Slide 1: Black Friday is Friday. | Your 7-day store SEO checklist. One job per day. Slide 2: Rule for this week | No redesigns. No new apps. No URL changes. Protect what works. Slide 3: Monday: Is your seasonal page indexed? | Search Console → URL Inspection → your /black-friday URL. If not indexed, request indexing. Slide 4: Tuesday: Links | Homepage banner and main menu both link to the seasonal hub. Hub links to every deal collection. Slide 5: Wednesday: Prices | Sale price on page = price in structured data = price in Merchant Center feed. Slide 6: Thursday: Speed | Test your top 5 sale pages on PageSpeed Insights, mobile. Remove anything heavy you added for the sale. Slide 7: Friday: Stock | Products sell out. Keep the pages live, show "back soon", link alternatives. Slide 8: Saturday: Errors | Search Console → Pages. Any sale URLs not indexed or returning errors? Slide 9: Sunday: Cyber Monday | Update the same hub page for Cyber Monday. Don't create a new URL. Slide 10: Comment "LAUNCHWEEK" | Get the Black Friday Week SEO Checklist. Follow Mehrooz for more store SEO. | T20: Design a 10-slide LinkedIn PDF carousel, 1080x1350 each. Clean premium editorial style: off-white #F4F7FD background, primary blue #1566D7 accents, navy #191A46 text, headlines in Bebas Neue (bold condensed, all caps), body in Inter; generous margins, faint grid lines, crisp vector icons, no stock-photo clutter. Cover slide like a premium guide cover: giant two-tone headline (key word in blue), small illustration/UI mockup, numbered contents list. Inner slides: big slide number in blue, Bebas Neue title, short Inter body, one diagram/mockup/checklist per slide. Last slide: navy CTA banner with download icon. SLIDE CONTENT: Slide 1: Black Friday is Friday. | Your 7-day store SEO checklist. One job per day. Slide 2: Rule for this week | No redesigns. No new apps. No URL changes. Protect what works. Slide 3: Monday: Is your seasonal page indexed? | Search Console → URL Inspection → your /black-friday URL. If not indexed, request indexing. Slide 4: Tuesday: Links | Homepage banner and main menu both link to the seasonal hub. Hub links to every deal collection. Slide 5: Wednesday: Prices | Sale price on page = price in structured data = price in Merchant Center feed. Slide 6: Thursday: Speed | Test your top 5 sale pages on PageSpeed Insights, mobile. Remove anything heavy you added for the sale. Slide 7: Friday: Stock | Products sell out. Keep the pages live, show "back soon", link alternatives. Slide 8: Saturday: Errors | Search Console → Pages. Any sale URLs not indexed or returning errors? Slide 9: Sunday: Cyber Monday | Update the same hub page for Cyber Monday. Don't create a new URL. Slide 10: Comment "LAUNCHWEEK" | Get the Black Friday Week SEO Checklist. Follow Mehrooz for more store SEO. Footer on every frame: small circular headshot avatar + name tag 'Muhammad Mehrooz Shafique · Co-Founder, Permanent SEO' bottom-left; Permanent SEO 'P' logo (rising bar-chart + arrow mark) bottom-right. All text spelled exactly as written, sharp and legible on mobile; no extra words, no watermarks. | U20: Design a 10-slide Instagram carousel, 1080x1350 each. Bold creator style: deep gradient background #345DF5 (top) to #191A46 (bottom), huge white Bebas Neue / Anton condensed headline, key words highlighted in #1566D7 highlight boxes or light-blue text, high contrast. Slide 1 = scroll-stopping cover with giant condensed headline and a 'swipe →' cue; inner slides alternate navy and white backgrounds, big blue slide number, max 25 words, one icon or mini-diagram each; last slide = CTA with comment keyword in a blue pill. SLIDE CONTENT: Slide 1: Black Friday is Friday. | Your 7-day store SEO checklist. One job per day. Slide 2: Rule for this week | No redesigns. No new apps. No URL changes. Protect what works. Slide 3: Monday: Is your seasonal page indexed? | Search Console → URL Inspection → your /black-friday URL. If not indexed, request indexing. Slide 4: Tuesday: Links | Homepage banner and main menu both link to the seasonal hub. Hub links to every deal collection. Slide 5: Wednesday: Prices | Sale price on page = price in structured data = price in Merchant Center feed. Slide 6: Thursday: Speed | Test your top 5 sale pages on PageSpeed Insights, mobile. Remove anything heavy you added for the sale. Slide 7: Friday: Stock | Products sell out. Keep the pages live, show "back soon", link alternatives. Slide 8: Saturday: Errors | Search Console → Pages. Any sale URLs not indexed or returning errors? Slide 9: Sunday: Cyber Monday | Update the same hub page for Cyber Monday. Don't create a new URL. Slide 10: Comment "LAUNCHWEEK" | Get the Black Friday Week SEO Checklist. Follow Mehrooz for more store SEO. Footer on every frame: small circular headshot avatar + name tag 'Muhammad Mehrooz Shafique · Co-Founder, Permanent SEO' bottom-left; Permanent SEO 'P' logo (rising bar-chart + arrow mark) bottom-right. All text spelled exactly as written, sharp and legible on mobile; no extra words, no watermarks. | V20: LAUNCHWEEK | W20: Black Friday Week SEO Checklist (7-day printable PDF) | X20: Black Friday is Friday. This isn't the week for a redesign. It's the week to make sure nothing breaks. 7-day store SEO checklist, one job per day --- Mon: Is your /black-friday page indexed? Check with URL Inspection in Search Console. Tue: Homepage and main menu link to the seasonal hub. --- Wed: Sale price on the page = structured data = Merchant Center feed. Thu: Test your top 5 sale pages for mobile speed. --- Fri: Products will sell out. Keep the pages live and link alternatives. Sat: Check the Pages report for errors on sale URLs. --- Sun: Update the same hub for Cyber Monday. Don't create a new URL. --- One rule all week: no new apps, no theme changes, no URL changes. Protect what already works. #BlackFriday #EcommerceSEO | Y20: Repost the Instagram caption + same visual | Z20: X thread · Facebook carousel · Reddit text post | AD20: r/shopify | AE20: A simple 7-day SEO checklist for Black Friday week (no big changes needed) | AF20: Black Friday week is not the time for big SEO projects, but there are a few checks worth doing so nothing breaks while traffic is high. Here's what I go through with stores, one job per day. Mon: Check your Black Friday page is indexed using URL Inspection in Search Console. Tue: Make sure the homepage and main menu link to your sale hub, and the hub links to each deal collection. Wed: Confirm sale prices match across the product page, structured data and your Merchant Center feed. Thu: Run your top 5 sale pages through PageSpeed Insights on mobile. Remove any heavy banner or app you added just for the sale. Fri: When products sell out, keep the pages live with a back-in-stock option and links to alternatives. Sat: Look at the Pages report for errors on sale URLs. Sun: Update the same page for Cyber Monday rather than creating a new URL. General rule: no new apps, theme edits or URL changes until December. What's the one thing that broke on your store during a past Black Friday? | AG20: 08:30 / 12:30 | AH20: Planned
A21: 17 | B21: 46350 | C21: Tue | D21: 4 | E21: Nov 2026 | F21: E-commerce SEO Foundations + Black Friday / Cyber Monday SEO | G21: Data & Insight | H21: POST | I21: LinkedIn Post (detailed image) | J21: Instagram Post (single image) | K21: Read your Search Console like a seasonal forecast | L21: Last November's Search Console data is this November's to-do list. | M21: search console year over year comparison | N21: seasonal search trends ecommerce, GSC compare dates, black friday search queries, seasonal keyword data | O21: Your best Black Friday forecast is already in your store's data. Search Console keeps 16 months of performance data. That means you can still see last November. Here's how to read it: 1. Performance → Date → Compare → this period vs the same period last year 2. Switch to Queries. Sort by "Difference" in impressions 3. Look for three groups: → Queries that grew last November and are already rising again: protect those pages this week → Queries that grew last November but are flat now: check if the page that ranked still exists → New queries with impressions but low clicks: rewrite those titles before Friday 4. Switch to Pages. Any URL that earned clicks last November and shows nothing now is worth checking. Deleted? Redirected? Not indexed? Your numbers: [YOUR GSC DATA: top 5 queries by YoY impression change] The image shows exactly which buttons to press. Comment "SEASONDATA" and I'll send you the Year-over-Year Search Console Review Template. #GoogleSearchConsole #EcommerceSEO #SEOData #BlackFriday | P21: #GoogleSearchConsole #EcommerceSEO #SEOData #BlackFriday | Q21: Last November's data = this November's to-do list. Search Console → Performance → Compare dates: → Queries rising again: protect those pages → Queries flat now: did the page get deleted? → High impressions, low clicks: rewrite titles Search Console keeps 16 months of data. Last November is still in there. Use it. Save this. Comment "SEASONDATA" for the Year-over-Year Search Console Review Template. #googlesearchconsole #seodata #ecommerceseo #shopifyseo #seotips #blackfriday #onlinestore #seoanalytics #woocommerce #ecommercetips #shopifystore #dataanalysis | R21: #googlesearchconsole #seodata #ecommerceseo #shopifyseo #seotips #blackfriday #onlinestore #seoanalytics #woocommerce #ecommercetips #shopifystore #dataanalysis | S21: Single image, annotated screenshot, 1080x1350. Headline: LAST NOVEMBER'S DATA IS THIS NOVEMBER'S TO-DO LIST. Sub-headline: Search Console year-over-year in 4 clicks. Main visual: a stylised (not real-client) Search Console Performance screen with numbered annotation circles: ① Date filter → "Compare" tab → "Same period last year" ② Queries tab ③ Sort by "Impressions difference" ④ Pages tab Right-side legend, three colour-coded rows matching highlighted query rows in the mock table: GREEN "Rising again" → protect these pages this week AMBER "Flat now" → check the old page still exists BLUE "High impressions, low clicks" → rewrite title before Friday Mock table uses placeholder rows: [query 1] [query 2] [query 3] with [X] values (no fake numbers). Note strip: "Search Console stores 16 months of performance data." Footer: Mehrooz Shafique · Permanent SEO | Banner: Comment "SEASONDATA" for the template | T21: Create a 1080x1350 LinkedIn infographic. Clean premium editorial style: off-white #F4F7FD background, primary blue #1566D7 accents, navy #191A46 text, headlines in Bebas Neue (bold condensed, all caps), body in Inter; generous margins, faint grid lines, crisp vector icons, no stock-photo clutter. HEADLINE: "Last November's Search Console data is this November's to-do list." SUBHEAD: "Read your Search Console like a seasonal forecast" MAIN VISUAL: the layout described below containing exactly: Single image, annotated screenshot, 1080x1350. Headline: LAST NOVEMBER'S DATA IS THIS NOVEMBER'S TO-DO LIST. Sub-headline: Search Console year-over-year in 4 clicks. Main visual: a stylised (not real-client) Search Console Performance screen with numbered annotation circles: ① Date filter → "Compare" tab → "Same period last year" ② Queries tab ③ Sort by "Impressions difference" ④ Pages tab Right-side legend, three colour-coded rows matching highlighted query rows in the mock table: GREEN "Rising again" → protect these pages this week AMBER "Flat now" → check the old page still exists BLUE "High impressions, low clicks" → rewrite title before Friday Mock table uses placeholder rows: [query 1] [query 2] [query 3] with [X] values (no fake numbers). Note strip: "Search Console stores 16 months of performance data." Footer: Mehrooz Shafique · Permanent SEO | Banner: Comment "SEASONDATA" for the template CTA BANNER (bottom, navy rounded box, white text, keyword in blue): Comment "SEASONDATA" for Year-over-Year Search Console Review Template (Google Sheet) Footer on every frame: small circular headshot avatar + name tag 'Muhammad Mehrooz Shafique · Co-Founder, Permanent SEO' bottom-left; Permanent SEO 'P' logo (rising bar-chart + arrow mark) bottom-right. All text spelled exactly as written, sharp and legible on mobile; no extra words, no watermarks. | U21: Create a 1080x1350 Instagram post. Bold creator style: deep gradient background #345DF5 (top) to #191A46 (bottom), huge white Bebas Neue / Anton condensed headline, key words highlighted in #1566D7 highlight boxes or light-blue text, high contrast. HEADLINE (top, 2–3 lines, giant): "Last November's Search Console data is this November's to-do list." BODY (numbered points / simple visual): the 3–5 key points from this brief, shortened to max 8 words each: Single image, annotated screenshot, 1080x1350. Headline: LAST NOVEMBER'S DATA IS THIS NOVEMBER'S TO-DO LIST. Sub-headline: Search Console year-over-year in 4 clicks. Main visual: a stylised (not real-client) Search Console Performance screen with numbered annotation circles: ① Date filter → "Compare" tab → "Same period last year" ② Queries tab ③ Sort by "Impressions difference" ④ Pages tab Right-side legend, three colour-coded rows matching highlighted query rows in the mock table: GREEN "Rising again" → protect these pages this week AMBER "Flat now" → check the old page still exists BLUE "High impressions, low clicks" → rewrite title before Friday Mock table uses placeholder rows: [query 1] [query 2] [query 3] with [X] values (no fake numbers). Note strip: "Search Console stores 16 months of performance data." Footer: Mehrooz Shafique · Permanent SEO | Banner: Comment "SEASONDATA" for the template BOTTOM BAR: Comment "SEASONDATA" for Year-over-Year Search Console Review Template (Google Sheet) Footer on every frame: small circular headshot avatar + name tag 'Muhammad Mehrooz Shafique · Co-Founder, Permanent SEO' bottom-left; Permanent SEO 'P' logo (rising bar-chart + arrow mark) bottom-right (white versions). All text spelled exactly as written, sharp and legible on mobile; no extra words, no watermarks. | V21: SEASONDATA | W21: Year-over-Year Search Console Review Template (Google Sheet) | X21: Search Console keeps 16 months of data. Last November is still in there. Performance → Compare → same period last year → Queries. Rising again → protect. Flat → check the page still exists. Low CTR → rewrite the title. #SEO | Y21: Repost the Instagram caption + same visual | Z21: X post + image · Facebook image post | AG21: 08:30 / 18:30 | AH21: Planned
A22: 18 | B22: 46351 | C22: Wed | D22: 4 | E22: Nov 2026 | F22: E-commerce SEO Foundations + Black Friday / Cyber Monday SEO | G22: Myth-Busting | H22: REEL | I22: LinkedIn native vertical video | J22: Instagram Reel (9:16) | K22: Myth: more traffic means more sales | L22: We don't chase traffic. We chase buying searches. | M22: ecommerce keyword intent | N22: buying intent keywords, commercial keywords ecommerce, transactional keywords, organic revenue SEO | O22: A store can double its traffic and not sell one extra product. It happens when the traffic comes from the wrong searches. Blog posts ranking for "what is linen". Visitors who read and leave. The graph goes up. Revenue doesn't. Before chasing more traffic, we ask three questions: → Is this search from someone ready to buy, or just curious? → Does it land on a page where they can actually buy? → Is there a clear next step on that page? This week especially, focus on searches with buying words in them: "buy", "sale", "deal", "black friday", brand + product names, sizes and colours. Traffic is a number. Revenue is the point. Comment "BUYINTENT" and I'll send you the Buying-Intent Keyword Finder Sheet. #EcommerceSEO #KeywordResearch #SearchIntent #BlackFriday | P22: #EcommerceSEO #KeywordResearch #SearchIntent #BlackFriday | Q22: More traffic doesn't always mean more sales. Ask 3 questions: → Is this searcher ready to buy? → Can they buy on the page they land on? → Is the next step clear? Focus on buying words: "sale", "deal", "black friday", model names, sizes. Traffic is a number. Revenue is the point. Comment "BUYINTENT" for the Buying-Intent Keyword Finder Sheet. #ecommerceseo #keywordresearch #searchintent #shopifyseo #seotips #onlinestore #blackfriday #ecommercetips #woocommerce #shopifystore #seostrategy #ecommercemarketing | R22: #ecommerceseo #keywordresearch #searchintent #shopifyseo #seotips #onlinestore #blackfriday #ecommercetips #woocommerce #shopifystore #seostrategy #ecommercemarketing | S22: [0-3s] VO: We don't chase traffic. | ON-SCREEN: WE DON'T CHASE TRAFFIC. | VISUAL: Traffic graph shooting up, then frozen [3-5s] VO: We chase searches from people ready to buy. | ON-SCREEN: WE CHASE BUYING SEARCHES. | VISUAL: Search bar typing "linen sheets black friday" [5-7s] VO: Most reports celebrate this. | ON-SCREEN: MOST REPORTS CELEBRATE: | VISUAL: Dashboard with confetti [7-8s] VO: Sessions. | ON-SCREEN: SESSIONS. | VISUAL: Number ticking up [8-9s] VO: Impressions. | ON-SCREEN: IMPRESSIONS. | VISUAL: Number ticking up [9-10s] VO: Rankings. | ON-SCREEN: RANKINGS. | VISUAL: Position badge [10-13s] VO: But first, three things need to be true. | ON-SCREEN: BUT FIRST, 3 THINGS | VISUAL: Three cards [13-16s] VO: Is the searcher ready to buy? | ON-SCREEN: 1. READY TO BUY? | VISUAL: Wallet icon [16-19s] VO: Can they buy on that page? | ON-SCREEN: 2. CAN THEY BUY HERE? | VISUAL: Add to cart button [19-22s] VO: Is the next step clear? | ON-SCREEN: 3. IS THE NEXT STEP CLEAR? | VISUAL: Arrow to checkout [22-25s] VO: Without that, more traffic doesn't create more sales. | ON-SCREEN: TRAFFIC ≠ SALES | VISUAL: Graph up, revenue line flat [25-27s] VO: It creates visitors. | ON-SCREEN: IT CREATES VISITORS. | VISUAL: Crowd walking past a shop [27-30s] VO: Traffic is a number. Revenue is the point. | ON-SCREEN: TRAFFIC IS A NUMBER. REVENUE IS THE POINT. | VISUAL: End card "Comment BUYINTENT" + @Mehrooz · Permanent SEO | T22: Same video as Instagram Reel (upload natively, 9:16, add captions). See Instagram prompt → | U22: Produce a 1080x1920 vertical reel, 25–35 s. Visual style: soft white studio background with subtle grid and soft corner shadows, mostly monochrome (black, grey, white) with ONE accent colour blue #1566D7; cinematic 3D objects (rocket, credit card, balance scale, puzzle pieces, magnifying glass, Google/Shopify-style app icons) that move in with motion blur; kinetic typography: bold geometric sans, one or two words per beat, key word in large grey/blue. Permanent SEO logo small at top-centre throughout. Voiceover: calm, deep, confident male narrator; measured pace (~130 words/min); a short pause between every line; no hype, no music drops over the voice; subtle minimal ambient bed + soft whoosh on text changes. BEATS: [0-3s] VO: We don't chase traffic. | ON-SCREEN: WE DON'T CHASE TRAFFIC. | VISUAL: Traffic graph shooting up, then frozen [3-5s] VO: We chase searches from people ready to buy. | ON-SCREEN: WE CHASE BUYING SEARCHES. | VISUAL: Search bar typing "linen sheets black friday" [5-7s] VO: Most reports celebrate this. | ON-SCREEN: MOST REPORTS CELEBRATE: | VISUAL: Dashboard with confetti [7-8s] VO: Sessions. | ON-SCREEN: SESSIONS. | VISUAL: Number ticking up [8-9s] VO: Impressions. | ON-SCREEN: IMPRESSIONS. | VISUAL: Number ticking up [9-10s] VO: Rankings. | ON-SCREEN: RANKINGS. | VISUAL: Position badge [10-13s] VO: But first, three things need to be true. | ON-SCREEN: BUT FIRST, 3 THINGS | VISUAL: Three cards [13-16s] VO: Is the searcher ready to buy? | ON-SCREEN: 1. READY TO BUY? | VISUAL: Wallet icon [16-19s] VO: Can they buy on that page? | ON-SCREEN: 2. CAN THEY BUY HERE? | VISUAL: Add to cart button [19-22s] VO: Is the next step clear? | ON-SCREEN: 3. IS THE NEXT STEP CLEAR? | VISUAL: Arrow to checkout [22-25s] VO: Without that, more traffic doesn't create more sales. | ON-SCREEN: TRAFFIC ≠ SALES | VISUAL: Graph up, revenue line flat [25-27s] VO: It creates visitors. | ON-SCREEN: IT CREATES VISITORS. | VISUAL: Crowd walking past a shop [27-30s] VO: Traffic is a number. Revenue is the point. | ON-SCREEN: TRAFFIC IS A NUMBER. REVENUE IS THE POINT. | VISUAL: End card "Comment BUYINTENT" + @Mehrooz · Permanent SEO Final 3 s: dark/navy end card with Permanent SEO logo, 'SEO for E-commerce Brands' and 'Comment "BUYINTENT"'. Burned-in captions. All text spelled exactly as written, sharp and legible on mobile; no extra words, no watermarks. | V22: BUYINTENT | W22: Buying-Intent Keyword Finder Sheet (Search Console filters + modifier list, Google Sheet) | X22: A store can double its traffic and not sell one more product. Before chasing traffic, ask: → Is this searcher ready to buy? → Can they buy on that page? → Is the next step clear? Traffic is a number. Revenue is the point. #EcommerceSEO | Y22: Repost the Instagram caption + same visual as Facebook Reel | Z22: YouTube Shorts · Facebook Reels · X video | AA22: Ecommerce Keyword Intent: Why More Traffic Doesn't Mean More Sales | AB22: Ecommerce keyword intent in 30 seconds: why traffic from the wrong searches doesn't sell, and three questions to ask before chasing any keyword. #Shorts | AC22: ecommerce keyword intent, buying intent keywords, transactional keywords, ecommerce SEO, shopify SEO, keyword research, search intent, black friday SEO, organic revenue, Permanent SEO | AG22: 12:00 / 19:00 | AH22: Planned
A23: 19 | B23: 46352 | C23: Thu | D23: 4 | E23: Nov 2026 | F23: E-commerce SEO Foundations + Black Friday / Cyber Monday SEO | G23: Explainer | H23: LONG_VIDEO | I23: LinkedIn Long Video (16:9) | J23: Instagram Reel (30–45 s vertical cut) | K23: The Permanent SEO approach: build once, rank every season | L23: Most SEO resets every season. Ours is built to stay. | M23: ecommerce SEO agency | N23: long term ecommerce SEO, Shopify SEO services, sustainable SEO strategy, Permanent SEO approach | O23: There's a reason our agency is called Permanent SEO. Most store SEO I see is temporary. A new page for every sale. A new tactic every quarter. Links that disappear. Rankings that drop the moment the work stops. We build the opposite way. Four parts: 1. Foundations first Indexing, canonicals, speed, site structure. If Google can't crawl it properly, nothing else sticks. 2. Pages that match intent Categories for comparing, products for buying, guides for learning. One intent, one URL. 3. Assets that compound Permanent seasonal pages. Collections with real content. Internal links that point authority where revenue is. 4. Visibility in AI search Clear entities, structured data and content that ChatGPT, Gemini and Google's AI features can understand and cite. No link farms. No tricks that work for a month. The goal is simple: work you pay for once keeps working next year. Comment "PERMANENT" and I'll send you our Permanent SEO Framework one-pager. #EcommerceSEO #PermanentSEO #ShopifySEO #SEOStrategy | P23: #EcommerceSEO #PermanentSEO #ShopifySEO #SEOStrategy | Q23: Most SEO resets every season. Ours is built to stay. 1. Foundations first 2. Pages that match intent 3. Assets that compound 4. Visibility in AI search No link farms. No one-month tricks. Work you pay for once keeps working next year. Share this with a store owner tired of starting over. Comment "PERMANENT" for the Permanent SEO Framework one-pager. #ecommerceseo #seostrategy #shopifyseo #seoagency #seotips #onlinestore #longtermgrowth #woocommerce #aisearch #ecommercetips #shopifystore #organicgrowth | R23: #ecommerceseo #seostrategy #shopifyseo #seoagency #seotips #onlinestore #longtermgrowth #woocommerce #aisearch #ecommercetips #shopifystore #organicgrowth | S23: Scene 1 [0-10s] VO: "New sale, new landing page. New quarter, new SEO tactic. And somehow... we're back where we started. Again." | VISUAL: Store owner on a hamster wheel made of calendar pages Scene 2 [10-20s] VO: "Let's be honest. Your store doesn't have a traffic problem. It has a reset problem. Every season the work disappears." | VISUAL: Traffic graph rising and falling in a saw pattern Scene 3 [20-30s] VO: "Pages deleted after the sale. Links that vanish. Rankings that fall the moment someone stops pushing." | VISUAL: Pages crumbling, links snapping Scene 4 [30-38s] VO: "That's why we built Permanent SEO. SEO that's built once and keeps working." | VISUAL: Logo, a solid foundation block lands Scene 5 [38-50s] VO: "First, foundations. Indexing, canonicals, speed and site structure. If Google can't crawl it properly, nothing else sticks." | VISUAL: Foundation layer with labels Scene 6 [50-62s] VO: "Second, pages that match intent. Categories to compare. Products to buy. Guides to learn." | VISUAL: Three page types slot onto the foundation Scene 7 [62-74s] VO: "Third, assets that compound. Permanent seasonal pages. Collections with real content. Internal links pointing to where revenue is." | VISUAL: Building grows a floor each year, labelled 2026, 2027, 2028 Scene 8 [74-86s] VO: "Fourth, visibility in AI search. Clear structured data and content ChatGPT and Google's AI features can understand." | VISUAL: AI answer panel citing the store Scene 9 [86-94s] VO: "No spam. No link farms. Here's what that looks like for a client: [CLIENT RESULT: organic revenue year over year]." | VISUAL: Placeholder results card Scene 10 [94-110s] VO: "Comment PERMANENT for the framework. Or book a free e-commerce SEO audit with Permanent SEO." | VISUAL: End card, keyword, Mehrooz + Permanent SEO | T23: Produce a 1920x1080 motion-graphics explainer, 60–120 s. Visual style: bright white/very light blue #F4F7FD canvas, floating UI mockups (Google results, Search Console charts, product pages, ChatGPT answers), kinetic typography where key words turn blue #1566D7, smooth parallax and soft shadows, occasional full-bleed blue #1566D7 scene with one giant word. Voiceover: calm, deep, confident male narrator; measured pace (~130 words/min); a short pause between every line; no hype, no music drops over the voice; subtle minimal ambient bed + soft whoosh on text changes. SCRIPT & SCENES: Scene 1 [0-10s] VO: "New sale, new landing page. New quarter, new SEO tactic. And somehow... we're back where we started. Again." | VISUAL: Store owner on a hamster wheel made of calendar pages Scene 2 [10-20s] VO: "Let's be honest. Your store doesn't have a traffic problem. It has a reset problem. Every season the work disappears." | VISUAL: Traffic graph rising and falling in a saw pattern Scene 3 [20-30s] VO: "Pages deleted after the sale. Links that vanish. Rankings that fall the moment someone stops pushing." | VISUAL: Pages crumbling, links snapping Scene 4 [30-38s] VO: "That's why we built Permanent SEO. SEO that's built once and keeps working." | VISUAL: Logo, a solid foundation block lands Scene 5 [38-50s] VO: "First, foundations. Indexing, canonicals, speed and site structure. If Google can't crawl it properly, nothing else sticks." | VISUAL: Foundation layer with labels Scene 6 [50-62s] VO: "Second, pages that match intent. Categories to compare. Products to buy. Guides to learn." | VISUAL: Three page types slot onto the foundation Scene 7 [62-74s] VO: "Third, assets that compound. Permanent seasonal pages. Collections with real content. Internal links pointing to where revenue is." | VISUAL: Building grows a floor each year, labelled 2026, 2027, 2028 Scene 8 [74-86s] VO: "Fourth, visibility in AI search. Clear structured data and content ChatGPT and Google's AI features can understand." | VISUAL: AI answer panel citing the store Scene 9 [86-94s] VO: "No spam. No link farms. Here's what that looks like for a client: [CLIENT RESULT: organic revenue year over year]." | VISUAL: Placeholder results card Scene 10 [94-110s] VO: "Comment PERMANENT for the framework. Or book a free e-commerce SEO audit with Permanent SEO." | VISUAL: End card, keyword, Mehrooz + Permanent SEO End card: Permanent SEO logo + 'Comment "PERMANENT"' + 'Muhammad Mehrooz Shafique · Co-Founder, Permanent SEO'. Burn in captions. All text spelled exactly as written, sharp and legible on mobile; no extra words, no watermarks. | U23: Produce a 1080x1920 vertical reel, 25–35 s. Visual style: soft white studio background with subtle grid and soft corner shadows, mostly monochrome (black, grey, white) with ONE accent colour blue #1566D7; cinematic 3D objects (rocket, credit card, balance scale, puzzle pieces, magnifying glass, Google/Shopify-style app icons) that move in with motion blur; kinetic typography: bold geometric sans, one or two words per beat, key word in large grey/blue. Permanent SEO logo small at top-centre throughout. Voiceover: calm, deep, confident male narrator; measured pace (~130 words/min); a short pause between every line; no hype, no music drops over the voice; subtle minimal ambient bed + soft whoosh on text changes. BEATS: Vertical 30–45 s cut of the long video: keep the opener, the problem line, the 3–4 steps as one-word beats and the CTA. Source script: Scene 1 [0-10s] VO: "New sale, new landing page. New quarter, new SEO tactic. And somehow... we're back where we started. Again." | VISUAL: Store owner on a hamster wheel made of calendar pages Scene 2 [10-20s] VO: "Let's be honest. Your store doesn't have a traffic problem. It has a reset problem. Every season the work disappears." | VISUAL: Traffic graph rising and falling in a saw pattern Scene 3 [20-30s] VO: "Pages deleted after the sale. Links that vanish. Rankings that fall the moment someone stops pushing." | VISUAL: Pages crumbling, links snapping Scene 4 [30-38s] VO: "That's why we built Permanent SEO. SEO that's built once and keeps working." | VISUAL: Logo, a solid foundation block lands Scene 5 [38-50s] VO: "First, foundations. Indexing, canonicals, speed and site structure. If Google can't crawl it properly, nothing else sticks." | VISUAL: Foundation layer with labels Scene 6 [50-62s] VO: "Second, pages that match intent. Categories to compare. Products to buy. Guides to learn." | VISUAL: Three page types slot onto the foundation Scene 7 [62-74s] VO: "Third, assets that compound. Permanent seasonal pages. Collections with real content. Internal links pointing to where revenue is." | VISUAL: Building grows a floor each year, labelled 2026, 2027, 2028 Scene 8 [74-86s] VO: "Fourth, visibility in AI search. Clear structured data and content ChatGPT and Google's AI features can understand." | VISUAL: AI answer panel citing the store Scene 9 [86-94s] VO: "No spam. No link farms. Here's what that looks like for a client: [CLIENT RESULT: organic revenue year over year]." | VISUAL: Placeholder results card Scene 10 [94-110s] VO: "Comment PERMANENT for the framework. Or book a free e-commerce SEO audit with Permanent SEO." | VISUAL: End card, keyword, Mehrooz + Permanent SEO Final 3 s: dark/navy end card with Permanent SEO logo, 'SEO for E-commerce Brands' and 'Comment "PERMANENT"'. Burned-in captions. All text spelled exactly as written, sharp and legible on mobile; no extra words, no watermarks. | V23: PERMANENT | W23: Permanent SEO Framework One-Pager (4-part e-commerce SEO framework, PDF) | X23: Most store SEO resets every season. Permanent SEO is built the other way: 1. Foundations first 2. Pages that match intent 3. Assets that compound 4. AI search visibility Work you pay for once should keep working next year. #EcommerceSEO | Y23: Repost the Instagram caption + same visual (upload 16:9 natively) | Z23: YouTube long video · Facebook native video · X clip (first 45 s) | AA23: Ecommerce SEO Agency Approach: Build Once, Rank Every Season | AB23: How an ecommerce SEO agency should build for the long term. Mehrooz Shafique explains the Permanent SEO framework: foundations, intent-matched pages, compounding assets and AI search visibility. | AC23: ecommerce SEO agency, shopify SEO services, long term SEO, SEO strategy, ecommerce SEO, AI search, seasonal SEO, technical SEO, woocommerce SEO, Permanent SEO | AG23: 08:30 / 18:30 | AH23: Planned
A24: 20 | B24: 46353 | C24: Fri | D24: 4 | E24: Nov 2026 | F24: E-commerce SEO Foundations + Black Friday / Cyber Monday SEO | G24: Proof & Freebie | H24: POST | I24: LinkedIn Post (detailed image) | J24: Instagram Post (single image) | K24: Black Friday day: what to watch in Search Console while it's live | L24: It's Black Friday. Here's what I'm watching today, hour by hour. | M24: black friday SEO monitoring | N24: search console realtime, black friday traffic monitoring, ecommerce peak day SEO, BFCM tracking | O24: It's Black Friday. Your SEO work for this sale is mostly done. Today is about catching problems fast. Here's what we watch for clients on the day: Morning → Search Console Performance with the 24-hour view: is the seasonal hub getting impressions? → Spot-check the hub and top deal collections load on mobile Midday → Out-of-stock products: still live, alternatives linked → Price checks: page vs Merchant Center feed Afternoon → Any sale page returning errors or redirects you didn't plan → Which queries are bringing visitors you didn't expect. Note them for next year Evening → Write down what broke, what worked, and what you'd change. Next November starts with this list. What to avoid today: theme edits, new apps, URL changes. Here's how last year compared for one client: [CLIENT RESULT: BFCM organic sessions/revenue YoY] Comment "LIVEWATCH" and I'll send you the Black Friday Day Monitoring Sheet. #BlackFriday #EcommerceSEO #GoogleSearchConsole #BFCM | P24: #BlackFriday #EcommerceSEO #GoogleSearchConsole #BFCM | Q24: It's Black Friday. What I'm watching today: Morning → seasonal hub impressions in Search Console Midday → out-of-stock pages + price checks Afternoon → errors on sale pages Evening → notes for next year No theme edits. No new apps. No URL changes today. Protect what already works. Save this for Cyber Monday too. Comment "LIVEWATCH" for the Black Friday Day Monitoring Sheet. #blackfriday #blackfriday2026 #bfcm #cybermonday #ecommerceseo #shopifyseo #googlesearchconsole #seotips #onlinestore #ecommercetips #shopifystore #holidaysales | R24: #blackfriday #blackfriday2026 #bfcm #cybermonday #ecommerceseo #shopifyseo #googlesearchconsole #seotips #onlinestore #ecommercetips #shopifystore #holidaysales | S24: Single image, timeline infographic, 1080x1350. Top tag: BLACK FRIDAY · 27 NOV. Headline: WHAT TO WATCH TODAY. Sub-headline: Black Friday SEO monitoring, hour by hour. Vertical timeline with four time blocks, each with an icon and 2 checks: MORNING (sun icon): Seasonal hub impressions — GSC 24-hour view | Mobile spot-check of hub + top collections MIDDAY (clock icon): Out-of-stock pages still live | Page price = Merchant Center price AFTERNOON (warning icon): Errors or surprise redirects on sale URLs | Unexpected queries → note for next year EVENING (notebook icon): What broke · What worked · What to change Red "DON'T TODAY" box: Theme edits · New apps · URL changes Proof tile: "Last year, one client: [CLIENT RESULT: BFCM organic revenue YoY]". Footer: Mehrooz Shafique · Permanent SEO | Banner: Comment "LIVEWATCH" for the monitoring sheet | T24: Create a 1080x1350 LinkedIn infographic. Clean premium editorial style: off-white #F4F7FD background, primary blue #1566D7 accents, navy #191A46 text, headlines in Bebas Neue (bold condensed, all caps), body in Inter; generous margins, faint grid lines, crisp vector icons, no stock-photo clutter. HEADLINE: "It's Black Friday. Here's what I'm watching today, hour by hour." SUBHEAD: "Black Friday day: what to watch in Search Console while it's live" MAIN VISUAL: the layout described below containing exactly: Single image, timeline infographic, 1080x1350. Top tag: BLACK FRIDAY · 27 NOV. Headline: WHAT TO WATCH TODAY. Sub-headline: Black Friday SEO monitoring, hour by hour. Vertical timeline with four time blocks, each with an icon and 2 checks: MORNING (sun icon): Seasonal hub impressions — GSC 24-hour view | Mobile spot-check of hub + top collections MIDDAY (clock icon): Out-of-stock pages still live | Page price = Merchant Center price AFTERNOON (warning icon): Errors or surprise redirects on sale URLs | Unexpected queries → note for next year EVENING (notebook icon): What broke · What worked · What to change Red "DON'T TODAY" box: Theme edits · New apps · URL changes Proof tile: "Last year, one client: [CLIENT RESULT: BFCM organic revenue YoY]". Footer: Mehrooz Shafique · Permanent SEO | Banner: Comment "LIVEWATCH" for the monitoring sheet CTA BANNER (bottom, navy rounded box, white text, keyword in blue): Comment "LIVEWATCH" for Black Friday Day Monitoring Sheet (hour-by-hour checklist + incident log, Google Sheet) Footer on every frame: small circular headshot avatar + name tag 'Muhammad Mehrooz Shafique · Co-Founder, Permanent SEO' bottom-left; Permanent SEO 'P' logo (rising bar-chart + arrow mark) bottom-right. All text spelled exactly as written, sharp and legible on mobile; no extra words, no watermarks. | U24: Create a 1080x1350 Instagram post. Bold creator style: deep gradient background #345DF5 (top) to #191A46 (bottom), huge white Bebas Neue / Anton condensed headline, key words highlighted in #1566D7 highlight boxes or light-blue text, high contrast. HEADLINE (top, 2–3 lines, giant): "It's Black Friday. Here's what I'm watching today, hour by hour." BODY (numbered points / simple visual): the 3–5 key points from this brief, shortened to max 8 words each: Single image, timeline infographic, 1080x1350. Top tag: BLACK FRIDAY · 27 NOV. Headline: WHAT TO WATCH TODAY. Sub-headline: Black Friday SEO monitoring, hour by hour. Vertical timeline with four time blocks, each with an icon and 2 checks: MORNING (sun icon): Seasonal hub impressions — GSC 24-hour view | Mobile spot-check of hub + top collections MIDDAY (clock icon): Out-of-stock pages still live | Page price = Merchant Center price AFTERNOON (warning icon): Errors or surprise redirects on sale URLs | Unexpected queries → note for next year EVENING (notebook icon): What broke · What worked · What to change Red "DON'T TODAY" box: Theme edits · New apps · URL changes Proof tile: "Last year, one client: [CLIENT RESULT: BFCM organic revenue YoY]". Footer: Mehrooz Shafique · Permanent SEO | Banner: Comment "LIVEWATCH" for the monitoring sheet BOTTOM BAR: Comment "LIVEWATCH" for Black Friday Day Monitoring Sheet (hour-by-hour checklist + incident log, Google Sheet) Footer on every frame: small circular headshot avatar + name tag 'Muhammad Mehrooz Shafique · Co-Founder, Permanent SEO' bottom-left; Permanent SEO 'P' logo (rising bar-chart + arrow mark) bottom-right (white versions). All text spelled exactly as written, sharp and legible on mobile; no extra words, no watermarks. | V24: LIVEWATCH | W24: Black Friday Day Monitoring Sheet (hour-by-hour checklist + incident log, Google Sheet) | X24: It's Black Friday. SEO today is about catching problems fast. → Hub impressions in Search Console (24h view) → Out-of-stock pages still live → Page price = feed price → Errors on sale URLs → Notes for next year No theme edits today. #BlackFriday | Y24: Repost the Instagram caption + same visual | Z24: X post + image · Facebook image post | AG24: 09:00 / 12:30 | AH24: Planned
A25: 21 | B25: 46356 | C25: Mon | D25: 5 | E25: Nov 2026 | F25: E-commerce SEO Foundations + Black Friday / Cyber Monday SEO | G25: Educate | H25: SLIDE | I25: LinkedIn Slide Post (PDF carousel) | J25: Instagram Slide Post (carousel) | K25: Cyber Monday and after: 8 SEO moves once the sale ends | L25: The sale ends tonight. Your Black Friday page shouldn't. | M25: what to do with black friday page after sale | N25: post black friday SEO, cyber monday SEO, after BFCM SEO, seasonal page off season | O25: It's Cyber Monday. By tomorrow, most stores will start deleting. Sale banners. Deal collections. The Black Friday page. Here's what to do instead, in order: 1. Keep /black-friday live. Switch it to "Our next sale is coming" with an email sign-up 2. Point the homepage banner to your Christmas gift hub, not a dead deal 3. Products that sold out: keep the pages, add restock alerts 4. Deal collections: merge into permanent collections or 301 them to the closest match 5. Save this week's Search Console data. Export top queries and pages 6. Note which queries surprised you. They're next year's content plan 7. Ask buyers for reviews. Fresh reviews help product pages for Christmas and beyond 8. Put a date in the diary for October 2027 to refresh the page Peak season ends. The pages that earned it don't have to. Swipe through for the full sequence. Comment "AFTERPEAK" and I'll send you the Post-BFCM SEO Wrap-Up Checklist. #CyberMonday #BlackFriday #EcommerceSEO #ShopifySEO | P25: #CyberMonday #BlackFriday #EcommerceSEO #ShopifySEO | Q25: The sale ends tonight. The page shouldn't. 1. Keep /black-friday live 2. Switch to "next sale coming" + email sign-up 3. Homepage banner → Christmas gifts 4. Sold-out products stay live 5. Merge or 301 deal collections 6. Export Search Console data 7. Ask buyers for reviews 8. Diary note: refresh in October Save this for tomorrow. Comment "AFTERPEAK" for the Post-BFCM SEO Wrap-Up Checklist. #cybermonday #blackfriday #bfcm #ecommerceseo #shopifyseo #seotips #onlinestore #ecommercetips #shopifystore #woocommerce #christmasshopping #smallbusiness | R25: #cybermonday #blackfriday #bfcm #ecommerceseo #shopifyseo #seotips #onlinestore #ecommercetips #shopifystore #woocommerce #christmasshopping #smallbusiness | S25: Slide 1: The sale ends tonight. Your Black Friday page shouldn't. | 8 SEO moves for Cyber Monday and after. Slide 2: Move 1: Keep the URL live | /black-friday stays. Switch the copy to "Our next sale is coming" + email sign-up. Slide 3: Move 2: Update the homepage | Banner points to your Christmas gift hub, not an expired deal. Slide 4: Move 3: Sold-out products | Keep the pages. Add restock alerts and alternatives. Slide 5: Move 4: Deal collections | Merge into permanent collections or 301 to the closest match. No 404s. Slide 6: Move 5: Export your data | Search Console → Performance → last 7 days vs last year. Save top queries and pages. Slide 7: Move 6: Surprising queries | Queries you didn't plan for are next year's content plan. Slide 8: Move 7: Reviews | Ask BFCM buyers for reviews. Fresh reviews help product pages through Christmas. Slide 9: Move 8: Diary note | October 2027: refresh the page. Same URL. More authority. Slide 10: Comment "AFTERPEAK" | Get the Post-BFCM SEO Wrap-Up Checklist. Follow Mehrooz. Next month: technical SEO for stores. | T25: Design a 10-slide LinkedIn PDF carousel, 1080x1350 each. Clean premium editorial style: off-white #F4F7FD background, primary blue #1566D7 accents, navy #191A46 text, headlines in Bebas Neue (bold condensed, all caps), body in Inter; generous margins, faint grid lines, crisp vector icons, no stock-photo clutter. Cover slide like a premium guide cover: giant two-tone headline (key word in blue), small illustration/UI mockup, numbered contents list. Inner slides: big slide number in blue, Bebas Neue title, short Inter body, one diagram/mockup/checklist per slide. Last slide: navy CTA banner with download icon. SLIDE CONTENT: Slide 1: The sale ends tonight. Your Black Friday page shouldn't. | 8 SEO moves for Cyber Monday and after. Slide 2: Move 1: Keep the URL live | /black-friday stays. Switch the copy to "Our next sale is coming" + email sign-up. Slide 3: Move 2: Update the homepage | Banner points to your Christmas gift hub, not an expired deal. Slide 4: Move 3: Sold-out products | Keep the pages. Add restock alerts and alternatives. Slide 5: Move 4: Deal collections | Merge into permanent collections or 301 to the closest match. No 404s. Slide 6: Move 5: Export your data | Search Console → Performance → last 7 days vs last year. Save top queries and pages. Slide 7: Move 6: Surprising queries | Queries you didn't plan for are next year's content plan. Slide 8: Move 7: Reviews | Ask BFCM buyers for reviews. Fresh reviews help product pages through Christmas. Slide 9: Move 8: Diary note | October 2027: refresh the page. Same URL. More authority. Slide 10: Comment "AFTERPEAK" | Get the Post-BFCM SEO Wrap-Up Checklist. Follow Mehrooz. Next month: technical SEO for stores. Footer on every frame: small circular headshot avatar + name tag 'Muhammad Mehrooz Shafique · Co-Founder, Permanent SEO' bottom-left; Permanent SEO 'P' logo (rising bar-chart + arrow mark) bottom-right. All text spelled exactly as written, sharp and legible on mobile; no extra words, no watermarks. | U25: Design a 10-slide Instagram carousel, 1080x1350 each. Bold creator style: deep gradient background #345DF5 (top) to #191A46 (bottom), huge white Bebas Neue / Anton condensed headline, key words highlighted in #1566D7 highlight boxes or light-blue text, high contrast. Slide 1 = scroll-stopping cover with giant condensed headline and a 'swipe →' cue; inner slides alternate navy and white backgrounds, big blue slide number, max 25 words, one icon or mini-diagram each; last slide = CTA with comment keyword in a blue pill. SLIDE CONTENT: Slide 1: The sale ends tonight. Your Black Friday page shouldn't. | 8 SEO moves for Cyber Monday and after. Slide 2: Move 1: Keep the URL live | /black-friday stays. Switch the copy to "Our next sale is coming" + email sign-up. Slide 3: Move 2: Update the homepage | Banner points to your Christmas gift hub, not an expired deal. Slide 4: Move 3: Sold-out products | Keep the pages. Add restock alerts and alternatives. Slide 5: Move 4: Deal collections | Merge into permanent collections or 301 to the closest match. No 404s. Slide 6: Move 5: Export your data | Search Console → Performance → last 7 days vs last year. Save top queries and pages. Slide 7: Move 6: Surprising queries | Queries you didn't plan for are next year's content plan. Slide 8: Move 7: Reviews | Ask BFCM buyers for reviews. Fresh reviews help product pages through Christmas. Slide 9: Move 8: Diary note | October 2027: refresh the page. Same URL. More authority. Slide 10: Comment "AFTERPEAK" | Get the Post-BFCM SEO Wrap-Up Checklist. Follow Mehrooz. Next month: technical SEO for stores. Footer on every frame: small circular headshot avatar + name tag 'Muhammad Mehrooz Shafique · Co-Founder, Permanent SEO' bottom-left; Permanent SEO 'P' logo (rising bar-chart + arrow mark) bottom-right. All text spelled exactly as written, sharp and legible on mobile; no extra words, no watermarks. | V25: AFTERPEAK | W25: Post-BFCM SEO Wrap-Up Checklist (8-step PDF + Search Console export guide) | X25: It's Cyber Monday. Tomorrow most stores start deleting sale pages. Don't. 8 SEO moves for after the sale --- 1. Keep /black-friday live. Switch it to "next sale coming" with an email sign-up. 2. Point the homepage banner to your Christmas gift hub. --- 3. Sold-out products: keep the pages, add restock alerts. 4. Deal collections: merge into permanent ones or 301 to the closest match. No 404s. --- 5. Export this week's Search Console queries and pages. 6. Queries you didn't plan for are next year's content plan. --- 7. Ask BFCM buyers for reviews. 8. Diary note for October 2027: refresh the same page. --- Peak season ends. The pages that earned it don't have to. #CyberMonday #EcommerceSEO | Y25: Repost the Instagram caption + same visual | Z25: X thread · Facebook carousel · Reddit text post | AD25: r/ecommerce | AE25: What to do with your Black Friday pages after Cyber Monday (instead of deleting them) | AF25: Every December a lot of stores delete their Black Friday pages and deal collections, then rebuild them from scratch next November. Here's what I'd do instead. 1. Keep the main Black Friday URL live. Change the copy to something like "our next sale is coming" with an email sign-up. Use a URL with no year in it. 2. Move your homepage banner to the Christmas or gift collection so it isn't pointing at an expired offer. 3. Keep sold-out product pages live with a restock option and links to similar products. 4. For temporary deal collections, either merge them into permanent collections or 301 redirect to the closest match, rather than leaving 404s. 5. Export your Search Console queries and pages for the sale period. It's useful next year. 6. Look for queries you didn't expect. They often point to pages you're missing. 7. Ask sale customers for reviews while the purchase is fresh. 8. Set a reminder for October to refresh the page. Do you keep your seasonal pages live year round, or do you take them down? Curious what's worked for people. | AG25: 08:30 / 12:30 | AH25: Planned
A26: 22 | B26: 46357 | C26: Tue | D26: 5 | E26: Dec 2026 | F26: Technical SEO for Online Stores (Shopify & WooCommerce) | G26: Data & Insight | H26: POST | I26: LinkedIn Post (detailed image) | J26: Instagram Post (single image) | K26: Shopify's duplicate product URLs: /collections/x/products/y explained | L26: Your Shopify product lives at 3+ URLs. Google picks one. | M26: shopify duplicate product urls | N26: shopify collections products url, shopify canonical tag, within: collection liquid, shopify internal linking, duplicate content shopify | O26: Your Shopify product lives at 3+ URLs. Google picks one. Every product on Shopify can be reached through: → /products/blue-hoodie → /collections/hoodies/products/blue-hoodie → /collections/sale/products/blue-hoodie Shopify adds a canonical tag pointing to /products/. Good. The problem is your theme. Many themes link to the collection path from every collection grid. So your internal links point to the duplicate, and the canonical says "not me". That is a mixed signal. Google usually follows the canonical, but you are still asking it to crawl thousands of extra URLs on a big catalog. The fix is small: → Find the product card snippet in your theme → Remove the "| within: collection" filter from the product link → Check internal links now point to /products/ only → Re-crawl with Screaming Frog or Sitebulb to confirm Ten minutes of theme work. Cleaner crawl paths for every product you sell. I put the exact steps, the Liquid snippet and a before/after crawl check into one SOP. Comment "DUPEPATH" and I'll send you the Shopify Collection Path Fix SOP (Google Doc + theme snippet). #ShopifySEO #TechnicalSEO #EcommerceSEO #Shopify | P26: #ShopifySEO #TechnicalSEO #EcommerceSEO #Shopify | Q26: Your Shopify product has 3+ URLs. → /products/blue-hoodie → /collections/hoodies/products/blue-hoodie → /collections/sale/products/blue-hoodie Shopify's canonical points to /products/. But your theme often links to the collection path. Mixed signals. Wasted crawling. Fix: remove "within: collection" from the product card link. Save this for your next store audit. Share it with your developer. Comment "DUPEPATH" for the Shopify Collection Path Fix SOP (Google Doc + theme snippet). #shopifyseo #technicalseo #ecommerceseo #shopify #shopifystore #seotips #onlinestore #ecommercetips #shopifyexperts #searchengineoptimization #googleseo #storeowner | R26: #shopifyseo #technicalseo #ecommerceseo #shopify #shopifystore #seotips #onlinestore #ecommercetips #shopifyexperts #searchengineoptimization #googleseo #storeowner | S26: Single image, 1080x1350 (IG) and 1200x1500 (LinkedIn). Dark navy background, white + lime accent. HEADLINE (top, bold condensed): ONE PRODUCT. THREE URLS. SUB-HEADLINE: Why Shopify themes create duplicate product paths CENTRE DIAGRAM: one product card ("Blue Hoodie") in the middle with three arrows pointing out to three URL boxes: Box 1 (green border, tick): /products/blue-hoodie — label "Canonical (the one Google should index)" Box 2 (red border, cross): /collections/hoodies/products/blue-hoodie — label "Duplicate path" Box 3 (red border, cross): /collections/sale/products/blue-hoodie — label "Duplicate path" CURVED ARROW from Box 2 and Box 3 back to Box 1 labelled "rel=canonical". LOWER PANEL titled "THE FIX (4 STEPS)": 1. Open snippets/product-card (or card-product.liquid) 2. Remove "| within: collection" from the product URL 3. Save and clear theme cache 4. Re-crawl: internal links should hit /products/ only SMALL CODE STRIP: {{ product.url | within: collection }} → {{ product.url }} FOOTER BANNER: Comment "DUPEPATH" for the SOP | Muhammad Mehrooz Shafique · Permanent SEO | T26: Create a 1080x1350 LinkedIn infographic. Clean premium editorial style: off-white #F4F7FD background, primary blue #1566D7 accents, navy #191A46 text, headlines in Bebas Neue (bold condensed, all caps), body in Inter; generous margins, faint grid lines, crisp vector icons, no stock-photo clutter. HEADLINE: "Your Shopify product lives at 3+ URLs. Google picks one." SUBHEAD: "Shopify's duplicate product URLs: /collections/x/products/y explained" MAIN VISUAL: the layout described below containing exactly: Single image, 1080x1350 (IG) and 1200x1500 (LinkedIn). Dark navy background, white + lime accent. HEADLINE (top, bold condensed): ONE PRODUCT. THREE URLS. SUB-HEADLINE: Why Shopify themes create duplicate product paths CENTRE DIAGRAM: one product card ("Blue Hoodie") in the middle with three arrows pointing out to three URL boxes: Box 1 (green border, tick): /products/blue-hoodie — label "Canonical (the one Google should index)" Box 2 (red border, cross): /collections/hoodies/products/blue-hoodie — label "Duplicate path" Box 3 (red border, cross): /collections/sale/products/blue-hoodie — label "Duplicate path" CURVED ARROW from Box 2 and Box 3 back to Box 1 labelled "rel=canonical". LOWER PANEL titled "THE FIX (4 STEPS)": 1. Open snippets/product-card (or card-product.liquid) 2. Remove "| within: collection" from the product URL 3. Save and clear theme cache 4. Re-crawl: internal links should hit /products/ only SMALL CODE STRIP: {{ product.url | within: collection }} → {{ product.url }} FOOTER BANNER: Comment "DUPEPATH" for the SOP | Muhammad Mehrooz Shafique · Permanent SEO CTA BANNER (bottom, navy rounded box, white text, keyword in blue): Comment "DUPEPATH" for Shopify Collection Path Fix SOP (Google Doc + theme snippet) Footer on every frame: small circular headshot avatar + name tag 'Muhammad Mehrooz Shafique · Co-Founder, Permanent SEO' bottom-left; Permanent SEO 'P' logo (rising bar-chart + arrow mark) bottom-right. All text spelled exactly as written, sharp and legible on mobile; no extra words, no watermarks. | U26: Create a 1080x1350 Instagram post. Bold creator style: deep gradient background #345DF5 (top) to #191A46 (bottom), huge white Bebas Neue / Anton condensed headline, key words highlighted in #1566D7 highlight boxes or light-blue text, high contrast. HEADLINE (top, 2–3 lines, giant): "Your Shopify product lives at 3+ URLs. Google picks one." BODY (numbered points / simple visual): the 3–5 key points from this brief, shortened to max 8 words each: Single image, 1080x1350 (IG) and 1200x1500 (LinkedIn). Dark navy background, white + lime accent. HEADLINE (top, bold condensed): ONE PRODUCT. THREE URLS. SUB-HEADLINE: Why Shopify themes create duplicate product paths CENTRE DIAGRAM: one product card ("Blue Hoodie") in the middle with three arrows pointing out to three URL boxes: Box 1 (green border, tick): /products/blue-hoodie — label "Canonical (the one Google should index)" Box 2 (red border, cross): /collections/hoodies/products/blue-hoodie — label "Duplicate path" Box 3 (red border, cross): /collections/sale/products/blue-hoodie — label "Duplicate path" CURVED ARROW from Box 2 and Box 3 back to Box 1 labelled "rel=canonical". LOWER PANEL titled "THE FIX (4 STEPS)": 1. Open snippets/product-card (or card-product.liquid) 2. Remove "| within: collection" from the product URL 3. Save and clear theme cache 4. Re-crawl: internal links should hit /products/ only SMALL CODE STRIP: {{ product.url | within: collection }} → {{ product.url }} FOOTER BANNER: Comment "DUPEPATH" for the SOP | Muhammad Mehrooz Shafique · Permanent SEO BOTTOM BAR: Comment "DUPEPATH" for Shopify Collection Path Fix SOP (Google Doc + theme snippet) Footer on every frame: small circular headshot avatar + name tag 'Muhammad Mehrooz Shafique · Co-Founder, Permanent SEO' bottom-left; Permanent SEO 'P' logo (rising bar-chart + arrow mark) bottom-right (white versions). All text spelled exactly as written, sharp and legible on mobile; no extra words, no watermarks. | V26: DUPEPATH | W26: Shopify Collection Path Fix SOP (Google Doc + theme snippet) | X26: Shopify gives every product 3+ URLs: /products/x and /collections/any/products/x. The canonical points to /products/. Your theme often links to the other ones. Fix: remove "| within: collection" from the product card link. #ShopifySEO #TechnicalSEO | Y26: Repost the Instagram caption + same visual | Z26: X post + image · Facebook image post | AG26: 08:30 / 18:30 | AH26: Planned
A27: 23 | B27: 46358 | C27: Wed | D27: 5 | E27: Dec 2026 | F27: Technical SEO for Online Stores (Shopify & WooCommerce) | G27: Myth-Busting | H27: REEL | I27: LinkedIn native vertical video | J27: Instagram Reel (9:16) | K27: Crawl budget on large catalogs: stop adding pages, fix crawl paths | L27: We don't add more pages. We fix where Google spends time. | M27: crawl budget ecommerce | N27: crawl budget shopify, large catalog seo, googlebot crawl stats, filter urls crawl, crawl waste | O27: We don't add more pages. We fix where Google spends its time. Crawl budget is not a problem for a 200-product store. It becomes one when you have tens of thousands of URLs: products, variants, filters, tags, sort orders, paginated collections. Google's own documentation says crawl budget mainly matters for large sites or sites with lots of auto-generated URLs. Most big online stores are both. Three checks I run first: → Are filter and sort URLs getting crawled? (GSC Crawl Stats, or server logs) → Are discontinued products still eating requests? → How long until a new product page is crawled and indexed? If the answers are bad, publishing more pages just adds noise. Fix the crawl paths first. Then grow the catalog. I built a sheet that walks through every check, with where to find the data in GSC and what "good" looks like. Comment "CRAWLBUDGET" and I'll send you the Large Catalog Crawl Budget Audit Sheet (Google Sheet). #TechnicalSEO #CrawlBudget #EcommerceSEO #ShopifySEO | P27: #TechnicalSEO #CrawlBudget #EcommerceSEO #ShopifySEO | Q27: We don't add more pages. We fix where Google spends time. Big catalog? Check 3 things first: → Filter and sort URLs being crawled → Dead products still eating requests → New pages taking weeks to get indexed More pages without clean crawl paths = more noise. Save this for your next store audit. Share it with your developer. Comment "CRAWLBUDGET" for the Large Catalog Crawl Budget Audit Sheet (Google Sheet). #technicalseo #crawlbudget #ecommerceseo #shopifyseo #woocommerce #seotips #onlinestore #googlesearchconsole #seoexpert #ecommercebusiness #searchengineoptimization #storeowner | R27: #technicalseo #crawlbudget #ecommerceseo #shopifyseo #woocommerce #seotips #onlinestore #googlesearchconsole #seoexpert #ecommercebusiness #searchengineoptimization #storeowner | S27: [0-2s] VO: We don't add more pages. | ON-SCREEN: WE DON'T ADD MORE PAGES. | VISUAL: Black screen, white kinetic type slams in [2-4s] VO: We fix where Google spends its time. | ON-SCREEN: WE FIX WHERE GOOGLE SPENDS ITS TIME. | VISUAL: Type shifts to lime, clock icon ticks [4-7s] VO: Most store owners do this. | ON-SCREEN: MOST STORE OWNERS DO THIS: | VISUAL: Grid of product thumbnails multiplying [7-8s] VO: More products. | ON-SCREEN: MORE PRODUCTS. | VISUAL: Word pops [8-9s] VO: More filters. | ON-SCREEN: MORE FILTERS. | VISUAL: Word pops [9-10s] VO: More tags. | ON-SCREEN: MORE TAGS. | VISUAL: Word pops [10-13s] VO: But on a big catalog, three things matter first. | ON-SCREEN: BUT FIRST, 3 THINGS. | VISUAL: Three empty boxes appear [13-16s] VO: Are filter URLs being crawled? | ON-SCREEN: 1. FILTER URLS CRAWLED? | VISUAL: Box 1 fills: URL with ?color=red&size=m [16-19s] VO: Are old products still eating requests? | ON-SCREEN: 2. DEAD PRODUCTS CRAWLED? | VISUAL: Box 2 fills: 404 tag [19-23s] VO: Is Google reaching your new pages fast? | ON-SCREEN: 3. NEW PAGES FOUND FAST? | VISUAL: Box 3 fills: calendar with delay [23-26s] VO: Without that, more pages don't add rankings. | ON-SCREEN: MORE PAGES ≠ MORE RANKINGS. | VISUAL: Crossed-out graph [26-28s] VO: They add noise. | ON-SCREEN: THEY ADD NOISE. | VISUAL: Static noise texture [28-32s] VO: A clean crawl path is how big stores grow. | ON-SCREEN: CLEAN CRAWL PATHS GROW STORES. | VISUAL: Logo + Comment CRAWLBUDGET | T27: Same video as Instagram Reel (upload natively, 9:16, add captions). See Instagram prompt → | U27: Produce a 1080x1920 vertical reel, 25–35 s. Visual style: soft white studio background with subtle grid and soft corner shadows, mostly monochrome (black, grey, white) with ONE accent colour blue #1566D7; cinematic 3D objects (rocket, credit card, balance scale, puzzle pieces, magnifying glass, Google/Shopify-style app icons) that move in with motion blur; kinetic typography: bold geometric sans, one or two words per beat, key word in large grey/blue. Permanent SEO logo small at top-centre throughout. Voiceover: calm, deep, confident male narrator; measured pace (~130 words/min); a short pause between every line; no hype, no music drops over the voice; subtle minimal ambient bed + soft whoosh on text changes. BEATS: [0-2s] VO: We don't add more pages. | ON-SCREEN: WE DON'T ADD MORE PAGES. | VISUAL: Black screen, white kinetic type slams in [2-4s] VO: We fix where Google spends its time. | ON-SCREEN: WE FIX WHERE GOOGLE SPENDS ITS TIME. | VISUAL: Type shifts to lime, clock icon ticks [4-7s] VO: Most store owners do this. | ON-SCREEN: MOST STORE OWNERS DO THIS: | VISUAL: Grid of product thumbnails multiplying [7-8s] VO: More products. | ON-SCREEN: MORE PRODUCTS. | VISUAL: Word pops [8-9s] VO: More filters. | ON-SCREEN: MORE FILTERS. | VISUAL: Word pops [9-10s] VO: More tags. | ON-SCREEN: MORE TAGS. | VISUAL: Word pops [10-13s] VO: But on a big catalog, three things matter first. | ON-SCREEN: BUT FIRST, 3 THINGS. | VISUAL: Three empty boxes appear [13-16s] VO: Are filter URLs being crawled? | ON-SCREEN: 1. FILTER URLS CRAWLED? | VISUAL: Box 1 fills: URL with ?color=red&size=m [16-19s] VO: Are old products still eating requests? | ON-SCREEN: 2. DEAD PRODUCTS CRAWLED? | VISUAL: Box 2 fills: 404 tag [19-23s] VO: Is Google reaching your new pages fast? | ON-SCREEN: 3. NEW PAGES FOUND FAST? | VISUAL: Box 3 fills: calendar with delay [23-26s] VO: Without that, more pages don't add rankings. | ON-SCREEN: MORE PAGES ≠ MORE RANKINGS. | VISUAL: Crossed-out graph [26-28s] VO: They add noise. | ON-SCREEN: THEY ADD NOISE. | VISUAL: Static noise texture [28-32s] VO: A clean crawl path is how big stores grow. | ON-SCREEN: CLEAN CRAWL PATHS GROW STORES. | VISUAL: Logo + Comment CRAWLBUDGET Final 3 s: dark/navy end card with Permanent SEO logo, 'SEO for E-commerce Brands' and 'Comment "CRAWLBUDGET"'. Burned-in captions. All text spelled exactly as written, sharp and legible on mobile; no extra words, no watermarks. | V27: CRAWLBUDGET | W27: Large Catalog Crawl Budget Audit Sheet (Google Sheet) | X27: We don't add more pages. We fix where Google spends its time. Big catalog? Check: → filter URLs crawled → dead products crawled → new pages slow to index More pages without clean crawl paths = noise. #TechnicalSEO #EcommerceSEO | Y27: Repost the Instagram caption + same visual as Facebook Reel | Z27: YouTube Shorts · Facebook Reels · X video | AA27: Crawl Budget for Ecommerce: Fix This Before Adding Pages | AB27: Crawl budget for ecommerce stores with large catalogs: three checks to run before you add more products, filters or tags. Muhammad Mehrooz Shafique from Permanent SEO explains in 30 seconds. #Shorts | AC27: crawl budget, ecommerce seo, shopify seo, technical seo, woocommerce seo, googlebot, crawl stats, large catalog seo, search console, permanent seo | AG27: 12:00 / 19:00 | AH27: Planned
